[
 {
  "index": 0,
  "data": {
   "link": "https://www.tulips.tsukuba.ac.jp/opac/volume/4034501?current=1&total=176&trans_url=%2Fopac%2Fsearch%3Farrivedwithin%3D1%26count%3D100%26defaultpage%3D1%26defaulttarget%3Dlocal%26order%3Darrival_date_d%26searchmode%3Dcomplex%26type%255B%255D%3Dbook",
   "title": "Aquinas and analogy, : pbk",
   "author": "Ralph McInerny",
   "publisher": "Catholic University of America Press 1996",
   "isbn": "0813209323",
   "holding": "\u4e2d\u592e 132.2-Th5 \u4e00\u822c\u56f3\u66f8",
   "status": "\u914d\u67b6\u6e08",
   "imagesrc": "https://books.google.com/books/content?id=yEp8gsdnw9AC&printsec=frontcover&img=1&zoom=5&edge=curl"
  }
 },
 {
  "index": 1,
  "data": {
   "link": "https://www.tulips.tsukuba.ac.jp/opac/volume/4034484?current=2&total=176&trans_url=%2Fopac%2Fsearch%3Farrivedwithin%3D1%26count%3D100%26defaultpage%3D1%26defaulttarget%3Dlocal%26order%3Darrival_date_d%26searchmode%3Dcomplex%26type%255B%255D%3Dbook",
   "title": "Being and some philosophers, 2nd ed., corr. and enl",
   "author": "Etienne Gilson",
   "publisher": "Pontifical Institute of Mediaeval Studies 1952",
   "isbn": "",
   "holding": "\u4e2d\u592e 111-G45 \u4e00\u822c\u56f3\u66f8",
   "status": "\u914d\u67b6\u6e08",
   "imagesrc": ""
  }
 },
 {
  "index": 2,
  "data": {
   "link": "https://www.tulips.tsukuba.ac.jp/opac/volume/4034552?current=3&total=176&trans_url=%2Fopac%2Fsearch%3Farrivedwithin%3D1%26count%3D100%26defaultpage%3D1%26defaulttarget%3Dlocal%26order%3Darrival_date_d%26searchmode%3Dcomplex%26type%255B%255D%3Dbook",
   "title": "The Cambridge companion to medieval philosophy, : pbk",
   "author": "edited by A.S. McGrade",
   "publisher": "Cambridge University Press 2003",
   "isbn": "9780521000635 / 0521000637",
   "holding": "\u4e2d\u592e 132-Ma15 \u4e00\u822c\u56f3\u66f8",
   "status": "\u914d\u67b6\u6e08",
   "imagesrc": "https://books.google.com/books/content?id=aaJE2rYeA5gC&printsec=frontcover&img=1&zoom=5&edge=curl"
  }
 },
 {
  "index": 3,
  "data": {
   "link": "https://www.tulips.tsukuba.ac.jp/opac/volume/4034198?current=4&total=176&trans_url=%2Fopac%2Fsearch%3Farrivedwithin%3D1%26count%3D100%26defaultpage%3D1%26defaulttarget%3Dlocal%26order%3Darrival_date_d%26searchmode%3Dcomplex%26type%255B%255D%3Dbook",
   "title": "Comparative study of low-grade metamorphism in the California Coast Ranges and the outer metamorphic belt of Japan",
   "author": "[by] W. G. Ernst ... [et.al.]",
   "publisher": "Geological Society of America 1970",
   "isbn": "081371124X",
   "holding": "\u4e2d\u592e 458.8-E68 \u4e00\u822c\u56f3\u66f8",
   "status": "\u914d\u67b6\u6e08",
   "imagesrc": "https://books.google.com/books/content?id=ZjmKLXc6OdoC&printsec=frontcover&img=1&zoom=5&edge=curl"
  }
 },
 {
  "index": 4,
  "data": {
   "link": "https://www.tulips.tsukuba.ac.jp/opac/volume/4034487?current=5&total=176&trans_url=%2Fopac%2Fsearch%3Farrivedwithin%3D1%26count%3D100%26defaultpage%3D1%26defaulttarget%3Dlocal%26order%3Darrival_date_d%26searchmode%3Dcomplex%26type%255B%255D%3Dbook",
   "title": "The complete works, : pbk",
   "author": "Pseudo-Dionysius/translation by Colm Luibh\u00e9id/foreword, notes, and translation collaboration by Paul Rorem/preface by Ren\u00e9 Roques/introductions by Jaroslav Pelikan, Jean Leclercq, and Karlfried Froehlich",
   "publisher": "Paulist Press 1987",
   "isbn": "0809128381",
   "holding": "\u4e2d\u592e 132.4-P95 \u4e00\u822c\u56f3\u66f8",
   "status": "\u914d\u67b6\u6e08",
   "imagesrc": "https://books.google.com/books/content?id=qFLpXKsNeVYC&printsec=frontcover&img=1&zoom=5&edge=curl"
  }
 },
 {
  "index": 5,
  "data": {
   "link": "https://www.tulips.tsukuba.ac.jp/opac/volume/4034516?current=6&total=176&trans_url=%2Fopac%2Fsearch%3Farrivedwithin%3D1%26count%3D100%26defaultpage%3D1%26defaulttarget%3Dlocal%26order%3Darrival_date_d%26searchmode%3Dcomplex%26type%255B%255D%3Dbook",
   "title": "The Concept of heart failure from Avicenna to Albertini",
   "author": "translations, commentaries and an essay by Saul Jarcho",
   "publisher": "Harvard University Press 1980",
   "isbn": "0674156358",
   "holding": "\u4e2d\u592e 493.235-J25 \u4e00\u822c\u56f3\u66f8",
   "status": "\u914d\u67b6\u6e08",
   "imagesrc": ""
  }
 },
 {
  "index": 6,
  "data": {
   "link": "https://www.tulips.tsukuba.ac.jp/opac/volume/4034494?current=7&total=176&trans_url=%2Fopac%2Fsearch%3Farrivedwithin%3D1%26count%3D100%26defaultpage%3D1%26defaulttarget%3Dlocal%26order%3Darrival_date_d%26searchmode%3Dcomplex%26type%255B%255D%3Dbook",
   "title": "De anima, : pbk, 1st ed",
   "author": "Aristotle/translated with an introduction and commentary by Christopher Shields",
   "publisher": "Clarendon Press 2016",
   "isbn": "9780199243457",
   "holding": "\u4e2d\u592e 131.4-Sh26 \u4e00\u822c\u56f3\u66f8",
   "status": "\u914d\u67b6\u6e08",
   "imagesrc": "https://books.google.com/books/content?id=xDDPsgEACAAJ&printsec=frontcover&img=1&zoom=5"
  }
 },
 {
  "index": 7,
  "data": {
   "link": "https://www.tulips.tsukuba.ac.jp/opac/volume/4034527?current=8&total=176&trans_url=%2Fopac%2Fsearch%3Farrivedwithin%3D1%26count%3D100%26defaultpage%3D1%26defaulttarget%3Dlocal%26order%3Darrival_date_d%26searchmode%3Dcomplex%26type%255B%255D%3Dbook",
   "title": "De la langue au pays : textes occitans et directions de recherches \u00e0 l'usage des classes du Ier cycle des Lyc\u00e9es et Coll\u00e8ges et des Cours compl\u00e9mentaires des pays languedociens",
   "author": "P. Lagarde, A. Lafont",
   "publisher": "Privat 1951",
   "isbn": "",
   "holding": "\u4e2d\u592e 801-L13 \u4e00\u822c\u56f3\u66f8",
   "status": "\u914d\u67b6\u6e08",
   "imagesrc": ""
  }
 },
 {
  "index": 8,
  "data": {
   "link": "https://www.tulips.tsukuba.ac.jp/opac/volume/4034479?current=9&total=176&trans_url=%2Fopac%2Fsearch%3Farrivedwithin%3D1%26count%3D100%26defaultpage%3D1%26defaulttarget%3Dlocal%26order%3Darrival_date_d%26searchmode%3Dcomplex%26type%255B%255D%3Dbook",
   "title": "Una donna in solitudine : sor Juana In\u00e9s de la Cruz : un'eccezione nella cultura e nella letteratura barocca",
   "author": "Dario Puccini",
   "publisher": "Cosmopoli 1996",
   "isbn": "8886740069",
   "holding": "\u4e2d\u592e 289-J87 \u4e00\u822c\u56f3\u66f8",
   "status": "\u914d\u67b6\u6e08",
   "imagesrc": "https://books.google.com/books/content?id=n5ZfAAAAMAAJ&printsec=frontcover&img=1&zoom=5"
  }
 },
 {
  "index": 9,
  "data": {
   "link": "https://www.tulips.tsukuba.ac.jp/opac/volume/4034205?current=10&total=176&trans_url=%2Fopac%2Fsearch%3Farrivedwithin%3D1%26count%3D100%26defaultpage%3D1%26defaulttarget%3Dlocal%26order%3Darrival_date_d%26searchmode%3Dcomplex%26type%255B%255D%3Dbook",
   "title": "Encyclopedia of European and Asian regional geology",
   "author": "edited by Eldridge M. Moores and Rhodes W. Fairbridge",
   "publisher": "Chapman & Hall 1997",
   "isbn": "0412740400",
   "holding": "\u4e2d\u592e 455.3-Mo43 \u53c2\u8003",
   "status": "\u914d\u67b6\u6e08",
   "imagesrc": "https://books.google.com/books/content?id=aYRup5mRcGsC&printsec=frontcover&img=1&zoom=5"
  }
 },
 {
  "index": 10,
  "data": {
   "link": "https://www.tulips.tsukuba.ac.jp/opac/volume/4034190?current=11&total=176&trans_url=%2Fopac%2Fsearch%3Farrivedwithin%3D1%26count%3D100%26defaultpage%3D1%26defaulttarget%3Dlocal%26order%3Darrival_date_d%26searchmode%3Dcomplex%26type%255B%255D%3Dbook",
   "title": "The evolving continents, 3rd ed",
   "author": "Brian F. Windley",
   "publisher": "Wiley 1995",
   "isbn": "0471917397",
   "holding": "\u4e2d\u592e 455-W76 \u4e00\u822c\u56f3\u66f8",
   "status": "\u914d\u67b6\u6e08",
   "imagesrc": "https://books.google.com/books/content?id=5GkSAQAAIAAJ&printsec=frontcover&img=1&zoom=5"
  }
 },
 {
  "index": 11,
  "data": {
   "link": "https://www.tulips.tsukuba.ac.jp/opac/volume/4034536?current=12&total=176&trans_url=%2Fopac%2Fsearch%3Farrivedwithin%3D1%26count%3D100%26defaultpage%3D1%26defaulttarget%3Dlocal%26order%3Darrival_date_d%26searchmode%3Dcomplex%26type%255B%255D%3Dbook",
   "title": "Feminist interpretations of Plato, : pbk",
   "author": "edited by Nancy Tuana",
   "publisher": "Pennsylvania State University Press 1994",
   "isbn": "0271010444",
   "holding": "\u4e2d\u592e 131.3-Tu1 \u4e00\u822c\u56f3\u66f8",
   "status": "\u914d\u67b6\u6e08",
   "imagesrc": "https://books.google.com/books/content?id=fef2-2cuh2wC&printsec=frontcover&img=1&zoom=5"
  }
 },
 {
  "index": 12,
  "data": {
   "link": "https://www.tulips.tsukuba.ac.jp/opac/volume/4034194?current=13&total=176&trans_url=%2Fopac%2Fsearch%3Farrivedwithin%3D1%26count%3D100%26defaultpage%3D1%26defaulttarget%3Dlocal%26order%3Darrival_date_d%26searchmode%3Dcomplex%26type%255B%255D%3Dbook",
   "title": "Fluids and basin evolution",
   "author": "edited by Kurt Kyser",
   "publisher": "Mineralogical Association of Canada 2000",
   "isbn": "092129428X",
   "holding": "\u4e2d\u592e 454.55-Ky7 \u4e00\u822c\u56f3\u66f8",
   "status": "\u914d\u67b6\u6e08",
   "imagesrc": "https://books.google.com/books/content?id=QVTwAAAAMAAJ&printsec=frontcover&img=1&zoom=5"
  }
 },
 {
  "index": 13,
  "data": {
   "link": "https://www.tulips.tsukuba.ac.jp/opac/volume/4034505?current=14&total=176&trans_url=%2Fopac%2Fsearch%3Farrivedwithin%3D1%26count%3D100%26defaultpage%3D1%26defaulttarget%3Dlocal%26order%3Darrival_date_d%26searchmode%3Dcomplex%26type%255B%255D%3Dbook",
   "title": "Gesuiti siciliani del '600 nel Celeste Impero : relazioni di lunga data tra Sicilia e Cina : atti del convegno, Palermo, 27 dicembre 2013",
   "author": "a cura di Giusi Tamburello",
   "publisher": "Salento Books 2014",
   "isbn": "9788849709889",
   "holding": "\u4e2d\u592e 198.25-Ta79 \u4e00\u822c\u56f3\u66f8",
   "status": "\u914d\u67b6\u6e08",
   "imagesrc": "https://books.google.com/books/content?id=UBovrgEACAAJ&printsec=frontcover&img=1&zoom=5"
  }
 },
 {
  "index": 14,
  "data": {
   "link": "https://www.tulips.tsukuba.ac.jp/opac/volume/4034480?current=15&total=176&trans_url=%2Fopac%2Fsearch%3Farrivedwithin%3D1%26count%3D100%26defaultpage%3D1%26defaulttarget%3Dlocal%26order%3Darrival_date_d%26searchmode%3Dcomplex%26type%255B%255D%3Dbook",
   "title": "G\u30dc\u30fc\u30eb\u6307\u5c0e\u30de\u30cb\u30e5\u30a2\u30eb, \u30d0\u30ea\u30a8\u30fc\u30b7\u30e7\u30f3\u7de8",
   "author": "",
   "publisher": "\u65e5\u672cG\u30dc\u30fc\u30eb\u5354\u4f1a 2017/4",
   "isbn": "",
   "holding": "\u4f53\u82b8 781-G29 \u4e00\u822c\u56f3\u66f8",
   "status": "\u914d\u67b6\u6e08",
   "imagesrc": ""
  }
 },
 {
  "index": 15,
  "data": {
   "link": "https://www.tulips.tsukuba.ac.jp/opac/volume/4034544?current=16&total=176&trans_url=%2Fopac%2Fsearch%3Farrivedwithin%3D1%26count%3D100%26defaultpage%3D1%26defaulttarget%3Dlocal%26order%3Darrival_date_d%26searchmode%3Dcomplex%26type%255B%255D%3Dbook",
   "title": "L'histoire de Pierre Olivi : franciscain pers\u00e9cut\u00e9, : EU",
   "author": "David Burr/traduction et pr\u00e9face de Fran\u00e7ois-Xavier Putallaz",
   "publisher": "\u00c9ditions universitaires, \u00c9ditions du Cerf 1997",
   "isbn": "2827107597",
   "holding": "\u4e2d\u592e 198.25-O59 \u4e00\u822c\u56f3\u66f8",
   "status": "\u914d\u67b6\u6e08",
   "imagesrc": ""
  }
 },
 {
  "index": 16,
  "data": {
   "link": "https://www.tulips.tsukuba.ac.jp/opac/volume/4034555?current=17&total=176&trans_url=%2Fopac%2Fsearch%3Farrivedwithin%3D1%26count%3D100%26defaultpage%3D1%26defaulttarget%3Dlocal%26order%3Darrival_date_d%26searchmode%3Dcomplex%26type%255B%255D%3Dbook",
   "title": "L'Image",
   "author": "Duns Scot/introduction, traduction, et notes par G\u00e9rard Sondag",
   "publisher": "J. Vrin 1993",
   "isbn": "2711611787",
   "holding": "\u4e2d\u592e 132.2-D97 \u4e00\u822c\u56f3\u66f8",
   "status": "\u914d\u67b6\u6e08",
   "imagesrc": "https://books.google.com/books/content?id=RyAfKbYwAUoC&printsec=frontcover&img=1&zoom=5&edge=curl"
  }
 },
 {
  "index": 17,
  "data": {
   "link": "https://www.tulips.tsukuba.ac.jp/opac/volume/4034534?current=18&total=176&trans_url=%2Fopac%2Fsearch%3Farrivedwithin%3D1%26count%3D100%26defaultpage%3D1%26defaulttarget%3Dlocal%26order%3Darrival_date_d%26searchmode%3Dcomplex%26type%255B%255D%3Dbook",
   "title": "Das Individuationsprinzip und seine Widerspiele in Natur und Geisteswelt, Geschichte und Gesellschaft",
   "author": "Herbert Cysarz",
   "publisher": "Universit\u00e4tsverlag Anton Pustet 1979",
   "isbn": "3702501665",
   "holding": "\u4e2d\u592e 111-C99 \u4e00\u822c\u56f3\u66f8",
   "status": "\u914d\u67b6\u6e08",
   "imagesrc": "https://books.google.com/books/content?id=nzs1AAAAIAAJ&printsec=frontcover&img=1&zoom=5"
  }
 },
 {
  "index": 18,
  "data": {
   "link": "https://www.tulips.tsukuba.ac.jp/opac/volume/4034537?current=19&total=176&trans_url=%2Fopac%2Fsearch%3Farrivedwithin%3D1%26count%3D100%26defaultpage%3D1%26defaulttarget%3Dlocal%26order%3Darrival_date_d%26searchmode%3Dcomplex%26type%255B%255D%3Dbook",
   "title": "Insolente libert\u00e9 : controverses et condamnations au XIIIe si\u00e8cle, : EU",
   "author": "Fran\u00e7ois-Xavier Putallaz",
   "publisher": "\u00c9ditions universitaires Fribourg, \u00c9ditions du Cerf 1995",
   "isbn": "2827107082",
   "holding": "\u4e2d\u592e 132-P98 \u4e00\u822c\u56f3\u66f8",
   "status": "\u914d\u67b6\u6e08",
   "imagesrc": "https://books.google.com/books/content?id=DszWAAAAMAAJ&printsec=frontcover&img=1&zoom=5"
  }
 },
 {
  "index": 19,
  "data": {
   "link": "https://www.tulips.tsukuba.ac.jp/opac/volume/4034521?current=20&total=176&trans_url=%2Fopac%2Fsearch%3Farrivedwithin%3D1%26count%3D100%26defaultpage%3D1%26defaulttarget%3Dlocal%26order%3Darrival_date_d%26searchmode%3Dcomplex%26type%255B%255D%3Dbook",
   "title": "John Duns Scotus, 1265-1965",
   "author": "edited by John K. Ryan and Bernardine M. Bonansea",
   "publisher": "Chatholic University of America Press 1965",
   "isbn": "",
   "holding": "\u4e2d\u592e 132.2-D97 \u4e00\u822c\u56f3\u66f8",
   "status": "\u914d\u67b6\u6e08",
   "imagesrc": ""
  }
 },
 {
  "index": 20,
  "data": {
   "link": "https://www.tulips.tsukuba.ac.jp/opac/volume/4034512?current=21&total=176&trans_url=%2Fopac%2Fsearch%3Farrivedwithin%3D1%26count%3D100%26defaultpage%3D1%26defaulttarget%3Dlocal%26order%3Darrival_date_d%26searchmode%3Dcomplex%26type%255B%255D%3Dbook",
   "title": "JSA\u30b7\u30cb\u30a2\u30dc\u30fc\u30eb\u30a8\u30af\u30b5\u30b5\u30a4\u30ba\u6307\u5c0e\u30de\u30cb\u30e5\u30a2\u30eb : \u547c\u5438\u3068\u59ff\u52e2\u306e\u305f\u3081\u306e\u30dc\u30fc\u30eb\u30a8\u30af\u30b5\u30b5\u30a4\u30ba",
   "author": "\u4e2d\u5c3e\u548c\u5b50\u8457",
   "publisher": "\u65e5\u672cG\u30dc\u30fc\u30eb\u5354\u4f1a 2011/2",
   "isbn": "",
   "holding": "\u4f53\u82b8 781-N41 \u4e00\u822c\u56f3\u66f8",
   "status": "\u914d\u67b6\u6e08",
   "imagesrc": ""
  }
 },
 {
  "index": 21,
  "data": {
   "link": "https://www.tulips.tsukuba.ac.jp/opac/volume/4034519?current=22&total=176&trans_url=%2Fopac%2Fsearch%3Farrivedwithin%3D1%26count%3D100%26defaultpage%3D1%26defaulttarget%3Dlocal%26order%3Darrival_date_d%26searchmode%3Dcomplex%26type%255B%255D%3Dbook",
   "title": "JSA\u30dc\u30fc\u30eb\u30a8\u30af\u30b5\u30b5\u30a4\u30ba\u6307\u5c0e\u30de\u30cb\u30e5\u30a2\u30eb, \u7b2c2\u7248",
   "author": "\u4e2d\u5c3e\u548c\u5b50\u8457",
   "publisher": "\u65e5\u672cG\u30dc\u30fc\u30eb\u5354\u4f1a 2012/8",
   "isbn": "",
   "holding": "\u4f53\u82b8 781-N41 \u4e00\u822c\u56f3\u66f8",
   "status": "\u914d\u67b6\u6e08",
   "imagesrc": ""
  }
 },
 {
  "index": 22,
  "data": {
   "link": "https://www.tulips.tsukuba.ac.jp/opac/volume/4034415?current=23&total=176&trans_url=%2Fopac%2Fsearch%3Farrivedwithin%3D1%26count%3D100%26defaultpage%3D1%26defaulttarget%3Dlocal%26order%3Darrival_date_d%26searchmode%3Dcomplex%26type%255B%255D%3Dbook",
   "title": "Law practice\u6c11\u4e8b\u8a34\u8a1f\u6cd5, \u7b2c4\u7248",
   "author": "\u5c71\u672c\u548c\u5f66\u7de8\u8457/\u5b89\u897f\u660e\u5b50 [\u307b\u304b] \u8457",
   "publisher": "\u5546\u4e8b\u6cd5\u52d9 2021/9",
   "isbn": "9784785728977",
   "holding": "\u5927\u585a 327.2-Y31 \u4e00\u822c\u56f3\u66f8",
   "status": "\u914d\u67b6\u6e08",
   "imagesrc": "https://books.google.com/books/content?id=rGKOzgEACAAJ&printsec=frontcover&img=1&zoom=5"
  }
 },
 {
  "index": 23,
  "data": {
   "link": "https://www.tulips.tsukuba.ac.jp/opac/volume/4034186?current=24&total=176&trans_url=%2Fopac%2Fsearch%3Farrivedwithin%3D1%26count%3D100%26defaultpage%3D1%26defaulttarget%3Dlocal%26order%3Darrival_date_d%26searchmode%3Dcomplex%26type%255B%255D%3Dbook",
   "title": "Major impacts and plate tectonics : a model for the Phanerozoic evolution of the earth's lithosphere, : pbk",
   "author": "Neville J. Price",
   "publisher": "Routledg 2001",
   "isbn": "0415238994",
   "holding": "\u4e2d\u592e 455.8-P93 \u4e00\u822c\u56f3\u66f8",
   "status": "\u914d\u67b6\u6e08",
   "imagesrc": ""
  }
 },
 {
  "index": 24,
  "data": {
   "link": "https://www.tulips.tsukuba.ac.jp/opac/volume/4034550?current=25&total=176&trans_url=%2Fopac%2Fsearch%3Farrivedwithin%3D1%26count%3D100%26defaultpage%3D1%26defaulttarget%3Dlocal%26order%3Darrival_date_d%26searchmode%3Dcomplex%26type%255B%255D%3Dbook",
   "title": "Mati\u00e8re, corps, esprit : la notion de sujet dans la philosophie de Thomas d'Aquin, : APF",
   "author": "Antonio Petagine",
   "publisher": "Academic Press, \u00c9ditions du Cerf 2014",
   "isbn": "9782827110889",
   "holding": "\u4e2d\u592e 132.2-Th5 \u4e00\u822c\u56f3\u66f8",
   "status": "\u914d\u67b6\u6e08",
   "imagesrc": ""
  }
 },
 {
  "index": 25,
  "data": {
   "link": "https://www.tulips.tsukuba.ac.jp/opac/volume/4034185?current=26&total=176&trans_url=%2Fopac%2Fsearch%3Farrivedwithin%3D1%26count%3D100%26defaultpage%3D1%26defaulttarget%3Dlocal%26order%3Darrival_date_d%26searchmode%3Dcomplex%26type%255B%255D%3Dbook",
   "title": "Meteorite impact! : the danger from space and South Africa's mega-impact : the Vredefort structure, : pbk, 3rd ed., completely rev",
   "author": "by Wolf Uwe Reimold and Roger L. Gibson/with a chapter by Anton Pelser, Mauritz Naud\u00e9 and Kevin Balkwill",
   "publisher": "Springer 2009",
   "isbn": "9783642104633 / 3642104630",
   "holding": "\u4e2d\u592e 455.48-R25 \u4e00\u822c\u56f3\u66f8",
   "status": "\u914d\u67b6\u6e08",
   "imagesrc": "https://books.google.com/books/content?id=_3m7DAEACAAJ&printsec=frontcover&img=1&zoom=5"
  }
 },
 {
  "index": 26,
  "data": {
   "link": "https://www.tulips.tsukuba.ac.jp/opac/volume/4034196?current=27&total=176&trans_url=%2Fopac%2Fsearch%3Farrivedwithin%3D1%26count%3D100%26defaultpage%3D1%26defaulttarget%3Dlocal%26order%3Darrival_date_d%26searchmode%3Dcomplex%26type%255B%255D%3Dbook",
   "title": "Modern approaches to ore and environmental mineralogy",
   "author": "editor, Louis J. Cabri and David J. Vaughan",
   "publisher": "Mineralogical Association of Canada 1998",
   "isbn": "092129400X",
   "holding": "\u4e2d\u592e 459-C11 \u4e00\u822c\u56f3\u66f8",
   "status": "\u914d\u67b6\u6e08",
   "imagesrc": "https://books.google.com/books/content?id=FNFPAQAAIAAJ&printsec=frontcover&img=1&zoom=5"
  }
 },
 {
  "index": 27,
  "data": {
   "link": "https://www.tulips.tsukuba.ac.jp/opac/volume/4034470?current=28&total=176&trans_url=%2Fopac%2Fsearch%3Farrivedwithin%3D1%26count%3D100%26defaultpage%3D1%26defaulttarget%3Dlocal%26order%3Darrival_date_d%26searchmode%3Dcomplex%26type%255B%255D%3Dbook",
   "title": "MOGA\u30e2\u30c0\u30f3\u30ac\u30fc\u30eb : \u30af\u30e9\u30d6\u5316\u7ca7\u54c1\u30fb\u30d7\u30e9\u30c8\u30f3\u793e\u306e\u30c7\u30b6\u30a4\u30f3",
   "author": "",
   "publisher": "\u9752\u5e7b\u820e 2021/7",
   "isbn": "9784861528460",
   "holding": "\u4f53\u82b8 674.9-M \u4e00\u822c\u56f3\u66f8",
   "status": "\u914d\u67b6\u6e08",
   "imagesrc": ""
  }
 },
 {
  "index": 28,
  "data": {
   "link": "https://www.tulips.tsukuba.ac.jp/opac/volume/4034499?current=29&total=176&trans_url=%2Fopac%2Fsearch%3Farrivedwithin%3D1%26count%3D100%26defaultpage%3D1%26defaulttarget%3Dlocal%26order%3Darrival_date_d%26searchmode%3Dcomplex%26type%255B%255D%3Dbook",
   "title": "The neo-Thomists, : pbk. : alk. paper",
   "author": "Gerald A. McCool",
   "publisher": "Marquette University Press, Association of Jesuit University Presses 1994",
   "isbn": "0874626013",
   "holding": "\u4e2d\u592e 132.2-Th5 \u4e00\u822c\u56f3\u66f8",
   "status": "\u914d\u67b6\u6e08",
   "imagesrc": "https://books.google.com/books/content?id=yu_jAAAAMAAJ&printsec=frontcover&img=1&zoom=5"
  }
 },
 {
  "index": 29,
  "data": {
   "link": "https://www.tulips.tsukuba.ac.jp/opac/volume/4034553?current=30&total=176&trans_url=%2Fopac%2Fsearch%3Farrivedwithin%3D1%26count%3D100%26defaultpage%3D1%26defaulttarget%3Dlocal%26order%3Darrival_date_d%26searchmode%3Dcomplex%26type%255B%255D%3Dbook",
   "title": "On creation : Quaestiones disputatae de potentia Dei, q. 3, : pbk",
   "author": "St. Thomas Aquinas/translated with introduction and notes by S.C. Selner-Wright",
   "publisher": "Catholic University of America Press 2011",
   "isbn": "9780813217987",
   "holding": "\u4e2d\u592e 132.2-Th5 \u4e00\u822c\u56f3\u66f8",
   "status": "\u914d\u67b6\u6e08",
   "imagesrc": "https://books.google.com/books/content?id=LXQ1gPPABQsC&printsec=frontcover&img=1&zoom=5&edge=curl"
  }
 },
 {
  "index": 30,
  "data": {
   "link": "https://www.tulips.tsukuba.ac.jp/opac/volume/4034520?current=31&total=176&trans_url=%2Fopac%2Fsearch%3Farrivedwithin%3D1%26count%3D100%26defaultpage%3D1%26defaulttarget%3Dlocal%26order%3Darrival_date_d%26searchmode%3Dcomplex%26type%255B%255D%3Dbook",
   "title": "Participation \u00e0 l'\u00eatre et histoire de la m\u00e9taphysique : essai de comparaison entre Cornelio Fabro et Jean-Fran\u00e7ois Courtine \u00e0 propos de l'esse thomiste",
   "author": "Ateneo Pontificio Regina Apostolorum Facolt\u00e0 di Filosofia",
   "publisher": "s.n. 2018",
   "isbn": "9781731031273",
   "holding": "\u4e2d\u592e 111-P25 \u4e00\u822c\u56f3\u66f8",
   "status": "\u914d\u67b6\u6e08",
   "imagesrc": ""
  }
 },
 {
  "index": 31,
  "data": {
   "link": "https://www.tulips.tsukuba.ac.jp/opac/volume/4034547?current=32&total=176&trans_url=%2Fopac%2Fsearch%3Farrivedwithin%3D1%26count%3D100%26defaultpage%3D1%26defaulttarget%3Dlocal%26order%3Darrival_date_d%26searchmode%3Dcomplex%26type%255B%255D%3Dbook",
   "title": "Penser avec Thomas d'Aquin, : EU",
   "author": "Louis-Bertrand Geiger/etudes thomistes pr\u00e9sent\u00e9es par Ruedi Imbach",
   "publisher": "\u00c9ditions universitaires, \u00c9ditions du Cerf 2000",
   "isbn": "2827108550",
   "holding": "\u4e2d\u592e 132.2-Th5 \u4e00\u822c\u56f3\u66f8",
   "status": "\u914d\u67b6\u6e08",
   "imagesrc": "https://books.google.com/books/content?id=IADD_2_iF5sC&printsec=frontcover&img=1&zoom=5&edge=curl"
  }
 },
 {
  "index": 32,
  "data": {
   "link": "https://www.tulips.tsukuba.ac.jp/opac/volume/4034511?current=33&total=176&trans_url=%2Fopac%2Fsearch%3Farrivedwithin%3D1%26count%3D100%26defaultpage%3D1%26defaulttarget%3Dlocal%26order%3Darrival_date_d%26searchmode%3Dcomplex%26type%255B%255D%3Dbook",
   "title": "Pens\u00e9es : Opuscules et lettres, : pbk",
   "author": "Blaise Pascal/Pens\u00e9es \u00e9dit\u00e9es par Philippe Sellier selon la copie de r\u00e9f\u00e9rence de Gilberte Pascal/Opuscules et lettres \u00e9dit\u00e9s par Laurence Plazenet et Philippe Sellier",
   "publisher": "Classiques Garnier 2010",
   "isbn": "9782812400957",
   "holding": "\u4e2d\u592e 135.25-Se47 \u4e00\u822c\u56f3\u66f8",
   "status": "\u914d\u67b6\u6e08",
   "imagesrc": ""
  }
 },
 {
  "index": 33,
  "data": {
   "link": "https://www.tulips.tsukuba.ac.jp/opac/volume/4034489?current=34&total=176&trans_url=%2Fopac%2Fsearch%3Farrivedwithin%3D1%26count%3D100%26defaultpage%3D1%26defaulttarget%3Dlocal%26order%3Darrival_date_d%26searchmode%3Dcomplex%26type%255B%255D%3Dbook",
   "title": "The philosophy of Peter Abelard, : pbk",
   "author": "John Marenbon",
   "publisher": "Cambridge University Press 1999",
   "isbn": "0521663997",
   "holding": "\u4e2d\u592e 132.2-A11 \u4e00\u822c\u56f3\u66f8",
   "status": "\u914d\u67b6\u6e08",
   "imagesrc": "https://books.google.com/books/content?id=ZLeahWCX8BkC&printsec=frontcover&img=1&zoom=5&edge=curl"
  }
 },
 {
  "index": 34,
  "data": {
   "link": "https://www.tulips.tsukuba.ac.jp/opac/volume/4034187?current=35&total=176&trans_url=%2Fopac%2Fsearch%3Farrivedwithin%3D1%26count%3D100%26defaultpage%3D1%26defaulttarget%3Dlocal%26order%3Darrival_date_d%26searchmode%3Dcomplex%26type%255B%255D%3Dbook",
   "title": "Physical geology : earth revealed, 7th ed",
   "author": "Diane H. Carlson, Charles C. Plummer, David McGeary",
   "publisher": "McGraw-Hill 2008",
   "isbn": "9780073050935 / 0073050938",
   "holding": "\u4e2d\u592e 450.12-C18 \u4e00\u822c\u56f3\u66f8",
   "status": "\u914d\u67b6\u6e08",
   "imagesrc": "https://books.google.com/books/content?id=lHgdAAAACAAJ&printsec=frontcover&img=1&zoom=5"
  }
 },
 {
  "index": 35,
  "data": {
   "link": "https://www.tulips.tsukuba.ac.jp/opac/volume/4034409?current=36&total=176&trans_url=%2Fopac%2Fsearch%3Farrivedwithin%3D1%26count%3D100%26defaultpage%3D1%26defaulttarget%3Dlocal%26order%3Darrival_date_d%26searchmode%3Dcomplex%26type%255B%255D%3Dbook",
   "title": "Primitive",
   "author": "\u5927\u69fb\u572d\u5b50\u8457",
   "publisher": "\u6c42\u9f8d\u5802 2021/3",
   "isbn": "9784763021052",
   "holding": "\u4f53\u82b8 753.8-O89 \u4e00\u822c\u56f3\u66f8",
   "status": "\u914d\u67b6\u6e08",
   "imagesrc": "https://books.google.com/books/content?id=i0GAzgEACAAJ&printsec=frontcover&img=1&zoom=5"
  }
 },
 {
  "index": 36,
  "data": {
   "link": "https://www.tulips.tsukuba.ac.jp/opac/volume/4034515?current=37&total=176&trans_url=%2Fopac%2Fsearch%3Farrivedwithin%3D1%26count%3D100%26defaultpage%3D1%26defaulttarget%3Dlocal%26order%3Darrival_date_d%26searchmode%3Dcomplex%26type%255B%255D%3Dbook",
   "title": "Python\u5b9f\u8df5AI\u30e2\u30c7\u30eb\u69cb\u7bc9100\u672c\u30ce\u30c3\u30af",
   "author": "\u4e0b\u5c71\u8f1d\u660c, \u4e2d\u6751\u667a, \u9ad8\u6728\u6d0b\u4ecb\u8457",
   "publisher": "\u79c0\u548c\u30b7\u30b9\u30c6\u30e0 2021/9",
   "isbn": "9784798064406",
   "holding": "\u56f3\u60c5\u642c\u9001\u4e2d 007.13-Sh55 \u4e00\u822c\u56f3\u66f8",
   "status": "\u914d\u67b6\u6e08",
   "imagesrc": "https://books.google.com/books/content?id=htRMEAAAQBAJ&printsec=frontcover&img=1&zoom=5&edge=curl"
  }
 },
 {
  "index": 37,
  "data": {
   "link": "https://www.tulips.tsukuba.ac.jp/opac/volume/4034496?current=38&total=176&trans_url=%2Fopac%2Fsearch%3Farrivedwithin%3D1%26count%3D100%26defaultpage%3D1%26defaulttarget%3Dlocal%26order%3Darrival_date_d%26searchmode%3Dcomplex%26type%255B%255D%3Dbook",
   "title": "Python\u3067\u306f\u3058\u3081\u308b\u6570\u7406\u6700\u9069\u5316 : \u30b1\u30fc\u30b9\u30b9\u30bf\u30c7\u30a3\u3067\u30e2\u30c7\u30ea\u30f3\u30b0\u306e\u30b9\u30ad\u30eb\u3092\u8eab\u306b\u3064\u3051\u3088\u3046",
   "author": "\u5ca9\u6c38\u4e8c\u90ce [\u307b\u304b] \u5171\u8457",
   "publisher": "\u30aa\u30fc\u30e0\u793e 2021/9",
   "isbn": "9784274227356",
   "holding": "\u56f3\u60c5\u642c\u9001\u4e2d 417-I95 \u4e00\u822c\u56f3\u66f8",
   "status": "\u914d\u67b6\u6e08",
   "imagesrc": "https://books.google.com/books/content?id=B-tBEAAAQBAJ&printsec=frontcover&img=1&zoom=5&edge=curl"
  }
 },
 {
  "index": 38,
  "data": {
   "link": "https://www.tulips.tsukuba.ac.jp/opac/volume/4034533?current=39&total=176&trans_url=%2Fopac%2Fsearch%3Farrivedwithin%3D1%26count%3D100%26defaultpage%3D1%26defaulttarget%3Dlocal%26order%3Darrival_date_d%26searchmode%3Dcomplex%26type%255B%255D%3Dbook",
   "title": "Questions 1-8 : le premier principe, l'individuation",
   "author": "Richard de Mediavilla/introduction, \u00e9dition critique et traduction par Alain Boureau",
   "publisher": "Belles Lettres 2012",
   "isbn": "9782251610030",
   "holding": "\u4e2d\u592e 191-R33 \u4e00\u822c\u56f3\u66f8",
   "status": "\u914d\u67b6\u6e08",
   "imagesrc": "https://books.google.com/books/content?id=s0D_wQEACAAJ&printsec=frontcover&img=1&zoom=5"
  }
 },
 {
  "index": 39,
  "data": {
   "link": "https://www.tulips.tsukuba.ac.jp/opac/volume/4034556?current=40&total=176&trans_url=%2Fopac%2Fsearch%3Farrivedwithin%3D1%26count%3D100%26defaultpage%3D1%26defaulttarget%3Dlocal%26order%3Darrival_date_d%26searchmode%3Dcomplex%26type%255B%255D%3Dbook",
   "title": "Reason and revelation in the middle ages",
   "author": "Etienne Gilson",
   "publisher": "",
   "isbn": "0684150263",
   "holding": "\u4e2d\u592e 135-G45 \u4e00\u822c\u56f3\u66f8",
   "status": "\u914d\u67b6\u6e08",
   "imagesrc": "https://books.google.com/books/content?id=krS4AAAAIAAJ&printsec=frontcover&img=1&zoom=5"
  }
 },
 {
  "index": 40,
  "data": {
   "link": "https://www.tulips.tsukuba.ac.jp/opac/volume/4034202?current=41&total=176&trans_url=%2Fopac%2Fsearch%3Farrivedwithin%3D1%26count%3D100%26defaultpage%3D1%26defaulttarget%3Dlocal%26order%3Darrival_date_d%26searchmode%3Dcomplex%26type%255B%255D%3Dbook",
   "title": "Silica, Silicates, pt. 2",
   "author": "John W. Anthony ... [et al.]",
   "publisher": "Mineral Data 1995",
   "isbn": "0962209716",
   "holding": "\u4e2d\u592e 459-A49-2-2 \u4e00\u822c\u56f3\u66f8",
   "status": "\u914d\u67b6\u6e08",
   "imagesrc": ""
  }
 },
 {
  "index": 41,
  "data": {
   "link": "https://www.tulips.tsukuba.ac.jp/opac/volume/4034201?current=42&total=176&trans_url=%2Fopac%2Fsearch%3Farrivedwithin%3D1%26count%3D100%26defaultpage%3D1%26defaulttarget%3Dlocal%26order%3Darrival_date_d%26searchmode%3Dcomplex%26type%255B%255D%3Dbook",
   "title": "Silica, Silicates, pt. 1",
   "author": "John W. Anthony ... [et al.]",
   "publisher": "Mineral Data 1995",
   "isbn": "0962209716",
   "holding": "\u4e2d\u592e 459-A49-2-1 \u4e00\u822c\u56f3\u66f8",
   "status": "\u914d\u67b6\u6e08",
   "imagesrc": ""
  }
 },
 {
  "index": 42,
  "data": {
   "link": "https://www.tulips.tsukuba.ac.jp/opac/volume/4034508?current=43&total=176&trans_url=%2Fopac%2Fsearch%3Farrivedwithin%3D1%26count%3D100%26defaultpage%3D1%26defaulttarget%3Dlocal%26order%3Darrival_date_d%26searchmode%3Dcomplex%26type%255B%255D%3Dbook",
   "title": "SRE\u306e\u63a2\u6c42 : \u69d8\u3005\u306a\u4f01\u696d\u306b\u304a\u3051\u308b\u30b5\u30a4\u30c8\u30ea\u30e9\u30a4\u30a2\u30d3\u30ea\u30c6\u30a3\u30a8\u30f3\u30b8\u30cb\u30a2\u30ea\u30f3\u30b0\u306e\u5c0e\u5165\u3068\u5b9f\u8df5",
   "author": "David N.Blank\u2010Edelman\u7de8/\u6e21\u9089\u4e86\u4ecb\u8a33",
   "publisher": "\u30aa\u30e9\u30a4\u30ea\u30fc\u30fb\u30b8\u30e3\u30d1\u30f3, \u30aa\u30fc\u30e0\u793e (\u767a\u58f2) 2021/9",
   "isbn": "9784873119618",
   "holding": "\u56f3\u60c5\u642c\u9001\u4e2d 007.63-B54 \u4e00\u822c\u56f3\u66f8",
   "status": "\u914d\u67b6\u6e08",
   "imagesrc": "https://books.google.com/books/content?id=2CiQzgEACAAJ&printsec=frontcover&img=1&zoom=5"
  }
 },
 {
  "index": 43,
  "data": {
   "link": "https://www.tulips.tsukuba.ac.jp/opac/volume/4034189?current=44&total=176&trans_url=%2Fopac%2Fsearch%3Farrivedwithin%3D1%26count%3D100%26defaultpage%3D1%26defaulttarget%3Dlocal%26order%3Darrival_date_d%26searchmode%3Dcomplex%26type%255B%255D%3Dbook",
   "title": "Subduction zone geodynamics",
   "author": "Serge Lallemand, Francesca Funicello, editors",
   "publisher": "Springer 2009",
   "isbn": "9783540879718",
   "holding": "\u4e2d\u592e 450.12-L14 \u4e00\u822c\u56f3\u66f8",
   "status": "\u914d\u67b6\u6e08",
   "imagesrc": "https://books.google.com/books/content?id=PhueDAEACAAJ&printsec=frontcover&img=1&zoom=5"
  }
 },
 {
  "index": 44,
  "data": {
   "link": "https://www.tulips.tsukuba.ac.jp/opac/volume/4034502?current=45&total=176&trans_url=%2Fopac%2Fsearch%3Farrivedwithin%3D1%26count%3D100%26defaultpage%3D1%26defaulttarget%3Dlocal%26order%3Darrival_date_d%26searchmode%3Dcomplex%26type%255B%255D%3Dbook",
   "title": "Les substances s\u00e9par\u00e9es",
   "author": "Thomas d'Aquin/traduction, introduction et notes de Nicolas Blanc",
   "publisher": "Belles lettres 2017",
   "isbn": "9782251446882",
   "holding": "\u4e2d\u592e 132.2-Th5 \u4e00\u822c\u56f3\u66f8",
   "status": "\u914d\u67b6\u6e08",
   "imagesrc": "https://books.google.com/books/content?id=Ta6xswEACAAJ&printsec=frontcover&img=1&zoom=5"
  }
 },
 {
  "index": 45,
  "data": {
   "link": "https://www.tulips.tsukuba.ac.jp/opac/volume/4034191?current=46&total=176&trans_url=%2Fopac%2Fsearch%3Farrivedwithin%3D1%26count%3D100%26defaultpage%3D1%26defaulttarget%3Dlocal%26order%3Darrival_date_d%26searchmode%3Dcomplex%26type%255B%255D%3Dbook",
   "title": "Suruga Bay, Japan : marine geology",
   "author": "Yoshifumi Misawa",
   "publisher": "Tokai University Press 1999",
   "isbn": "4486031431",
   "holding": "\u4e2d\u592e 452.8-Mi51 \u4e00\u822c\u56f3\u66f8",
   "status": "\u914d\u67b6\u6e08",
   "imagesrc": "https://books.google.com/books/content?id=91VPPQAACAAJ&printsec=frontcover&img=1&zoom=5"
  }
 },
 {
  "index": 46,
  "data": {
   "link": "https://www.tulips.tsukuba.ac.jp/opac/volume/4034554?current=47&total=176&trans_url=%2Fopac%2Fsearch%3Farrivedwithin%3D1%26count%3D100%26defaultpage%3D1%26defaulttarget%3Dlocal%26order%3Darrival_date_d%26searchmode%3Dcomplex%26type%255B%255D%3Dbook",
   "title": "Thomas Aquinas : a historical and philosophical profile",
   "author": "Pasquale Porro/translated by Joseph G. Trabbic & Roger W. Nutt",
   "publisher": "Catholic University of America Press 2016",
   "isbn": "9780813228051",
   "holding": "\u4e2d\u592e 132.2-Th5 \u4e00\u822c\u56f3\u66f8",
   "status": "\u914d\u67b6\u6e08",
   "imagesrc": "https://books.google.com/books/content?id=4rSOCwAAQBAJ&printsec=frontcover&img=1&zoom=5&edge=curl"
  }
 },
 {
  "index": 47,
  "data": {
   "link": "https://www.tulips.tsukuba.ac.jp/opac/volume/4034491?current=48&total=176&trans_url=%2Fopac%2Fsearch%3Farrivedwithin%3D1%26count%3D100%26defaultpage%3D1%26defaulttarget%3Dlocal%26order%3Darrival_date_d%26searchmode%3Dcomplex%26type%255B%255D%3Dbook",
   "title": "Thomas Aquinas's Summa contra gentiles : a guide and commentary, : pbk",
   "author": "Brian Davies",
   "publisher": "Oxford University Press 2016",
   "isbn": "9780190456542",
   "holding": "\u4e2d\u592e 132.2-Th5 \u4e00\u822c\u56f3\u66f8",
   "status": "\u914d\u67b6\u6e08",
   "imagesrc": "https://books.google.com/books/content?id=n-YRDAAAQBAJ&printsec=frontcover&img=1&zoom=5&edge=curl"
  }
 },
 {
  "index": 48,
  "data": {
   "link": "https://www.tulips.tsukuba.ac.jp/opac/volume/4034539?current=49&total=176&trans_url=%2Fopac%2Fsearch%3Farrivedwithin%3D1%26count%3D100%26defaultpage%3D1%26defaulttarget%3Dlocal%26order%3Darrival_date_d%26searchmode%3Dcomplex%26type%255B%255D%3Dbook",
   "title": "Thomas d'Aquin : De la v\u00e9rit\u00e9, question 2 (La science en Dieu), : EU",
   "author": "introduction, traduction et commentaire de Serge-Thomas Bonino/avec une pr\u00e9face de Ruedi Imbach",
   "publisher": "\u00c9ditions Universitaires, \u00c9ditions du Cerf 1996",
   "isbn": "2827107112",
   "holding": "\u4e2d\u592e 132.2-Th5 \u4e00\u822c\u56f3\u66f8",
   "status": "\u914d\u67b6\u6e08",
   "imagesrc": ""
  }
 },
 {
  "index": 49,
  "data": {
   "link": "https://www.tulips.tsukuba.ac.jp/opac/volume/4034466?current=50&total=176&trans_url=%2Fopac%2Fsearch%3Farrivedwithin%3D1%26count%3D100%26defaultpage%3D1%26defaulttarget%3Dlocal%26order%3Darrival_date_d%26searchmode%3Dcomplex%26type%255B%255D%3Dbook",
   "title": "VBT : \u30c8\u30ec\u30fc\u30cb\u30f3\u30b0\u306e\u52b9\u679c\u306f\u300c\u901f\u5ea6\u300d\u304c\u6c7a\u3081\u308b",
   "author": "\u9577\u8c37\u5ddd\u88d5\u8457",
   "publisher": "\u8349\u601d\u793e 2021/7",
   "isbn": "9784794225276",
   "holding": "\u4f53\u82b8 780.7-H36 \u4e00\u822c\u56f3\u66f8",
   "status": "\u914d\u67b6\u6e08",
   "imagesrc": "https://books.google.com/books/content?id=eyyMzgEACAAJ&printsec=frontcover&img=1&zoom=5"
  }
 },
 {
  "index": 50,
  "data": {
   "link": "https://www.tulips.tsukuba.ac.jp/opac/volume/4034485?current=51&total=176&trans_url=%2Fopac%2Fsearch%3Farrivedwithin%3D1%26count%3D100%26defaultpage%3D1%26defaulttarget%3Dlocal%26order%3Darrival_date_d%26searchmode%3Dcomplex%26type%255B%255D%3Dbook",
   "title": "Web\u6280\u8853\u304c\u3053\u308c1\u518a\u3067\u3057\u3063\u304b\u308a\u308f\u304b\u308b\u6559\u79d1\u66f8",
   "author": "\u9db4\u9577\u93ae\u4e00\u8457",
   "publisher": "\u6280\u8853\u8a55\u8ad6\u793e 2021/10",
   "isbn": "9784297123093",
   "holding": "\u56f3\u60c5\u642c\u9001\u4e2d 547.483-Ts85 \u4e00\u822c\u56f3\u66f8",
   "status": "\u914d\u67b6\u6e08",
   "imagesrc": "https://books.google.com/books/content?id=J5mKzgEACAAJ&printsec=frontcover&img=1&zoom=5"
  }
 },
 {
  "index": 51,
  "data": {
   "link": "https://www.tulips.tsukuba.ac.jp/opac/volume/4034522?current=52&total=176&trans_url=%2Fopac%2Fsearch%3Farrivedwithin%3D1%26count%3D100%26defaultpage%3D1%26defaulttarget%3Dlocal%26order%3Darrival_date_d%26searchmode%3Dcomplex%26type%255B%255D%3Dbook",
   "title": "\u3042\u3089\u304f\u308c/\u65b0\u4e16\u5e2f",
   "author": "\u5fb3\u7530\u79cb\u58f0\u4f5c",
   "publisher": "\u5ca9\u6ce2\u66f8\u5e97 2021/11",
   "isbn": "9784003102275",
   "holding": "\u4e2d\u592e 081-I95-G22-7 \u4e00\u822c\u56f3\u66f8, \u4f53\u82b8 081-I95-G22-7 \u4e00\u822c\u56f3\u66f8, \u533b\u5b66 081-I95-G22-7 \u4e00\u822c\u56f3\u66f8",
   "status": "\u914d\u67b6\u6e08",
   "imagesrc": "https://books.google.com/books/content?id=8cixzgEACAAJ&printsec=frontcover&img=1&zoom=5"
  }
 },
 {
  "index": 52,
  "data": {
   "link": "https://www.tulips.tsukuba.ac.jp/opac/volume/4034426?current=53&total=176&trans_url=%2Fopac%2Fsearch%3Farrivedwithin%3D1%26count%3D100%26defaultpage%3D1%26defaulttarget%3Dlocal%26order%3Darrival_date_d%26searchmode%3Dcomplex%26type%255B%255D%3Dbook",
   "title": "\u65b0\u305f\u306a\u5c55\u958b\u3092\u898b\u305b\u62e1\u5927\u3057\u7d9a\u3051\u308b\u30e0\u30fc\u30d6\u30e1\u30f3\u30c8\u306e\u672a\u6765",
   "author": "\u7b67\u8aa0\u4e00\u90ce\u8457",
   "publisher": "\u767d\u591c\u66f8\u623f 2021/9",
   "isbn": "9784864943451",
   "holding": "\u5927\u585a 798.5-Ka24-2 \u4e00\u822c\u56f3\u66f8",
   "status": "\u914d\u67b6\u6e08",
   "imagesrc": "https://books.google.com/books/content?id=Kv6LzgEACAAJ&printsec=frontcover&img=1&zoom=5"
  }
 },
 {
  "index": 53,
  "data": {
   "link": "https://www.tulips.tsukuba.ac.jp/opac/volume/4034542?current=54&total=176&trans_url=%2Fopac%2Fsearch%3Farrivedwithin%3D1%26count%3D100%26defaultpage%3D1%26defaulttarget%3Dlocal%26order%3Darrival_date_d%26searchmode%3Dcomplex%26type%255B%255D%3Dbook",
   "title": "\u6620\u753b\u3067\u5b66\u3076\u61b2\u6cd5, 2",
   "author": "\u5fd7\u7530\u967d\u5b50 [\u307b\u304b] \u7de8",
   "publisher": "\u6cd5\u5f8b\u6587\u5316\u793e 2021/6",
   "isbn": "9784589041593",
   "holding": "\u4e2d\u592e 323.04-Sh25-2 \u4e00\u822c\u56f3\u66f8",
   "status": "\u914d\u67b6\u6e08",
   "imagesrc": "https://books.google.com/books/content?id=vpZ-zgEACAAJ&printsec=frontcover&img=1&zoom=5"
  }
 },
 {
  "index": 54,
  "data": {
   "link": "https://www.tulips.tsukuba.ac.jp/opac/volume/4034195?current=55&total=176&trans_url=%2Fopac%2Fsearch%3Farrivedwithin%3D1%26count%3D100%26defaultpage%3D1%26defaulttarget%3Dlocal%26order%3Darrival_date_d%26searchmode%3Dcomplex%26type%255B%255D%3Dbook",
   "title": "\u89e3\u660e\u75c5\u7406\u5b66 : \u75c5\u6c17\u306e\u30e1\u30ab\u30cb\u30ba\u30e0\u3092\u89e3\u304f, \u7b2c4\u7248",
   "author": "\u52a0\u85e4\u5149\u4fdd, \u91d1\u4e95\u5f25\u6804, \u83c5\u91ce\u7950\u5e78\u7de8",
   "publisher": "\u533b\u6b6f\u85ac\u51fa\u7248 2021/11",
   "isbn": "9784263732038",
   "holding": "\u533b\u5b66 491.6-A58 \u4e00\u822c\u56f3\u66f8",
   "status": "\u914d\u67b6\u6e08",
   "imagesrc": "https://books.google.com/books/content?id=Z9KnzgEACAAJ&printsec=frontcover&img=1&zoom=5"
  }
 },
 {
  "index": 55,
  "data": {
   "link": "https://www.tulips.tsukuba.ac.jp/opac/volume/4034549?current=56&total=176&trans_url=%2Fopac%2Fsearch%3Farrivedwithin%3D1%26count%3D100%26defaultpage%3D1%26defaulttarget%3Dlocal%26order%3Darrival_date_d%26searchmode%3Dcomplex%26type%255B%255D%3Dbook",
   "title": "\u683c\u5dee\u793e\u4f1a\u8003 : \u30d6\u30e9\u30b8\u30eb\u306e\u8ca7\u56f0\u554f\u984c\u304b\u3089\u8003\u3048\u308b\u516c\u6b63\u306a\u793e\u4f1a",
   "author": "\u5965\u7530\u82e5\u83dc\u8457",
   "publisher": "\u795e\u7530\u5916\u8a9e\u5927\u5b66\u51fa\u7248\u5c40, \u307a\u308a\u304b\u3093\u793e (\u767a\u58f2) 2021/4",
   "isbn": "9784831530141",
   "holding": "\u4e2d\u592e 361.8-O54 \u4e00\u822c\u56f3\u66f8",
   "status": "\u914d\u67b6\u6e08",
   "imagesrc": "https://books.google.com/books/content?id=NeNazgEACAAJ&printsec=frontcover&img=1&zoom=5"
  }
 },
 {
  "index": 56,
  "data": {
   "link": "https://www.tulips.tsukuba.ac.jp/opac/volume/4034476?current=57&total=176&trans_url=%2Fopac%2Fsearch%3Farrivedwithin%3D1%26count%3D100%26defaultpage%3D1%26defaulttarget%3Dlocal%26order%3Darrival_date_d%26searchmode%3Dcomplex%26type%255B%255D%3Dbook",
   "title": "\u6f22\u5b57\u7b46\u9806\u30cf\u30f3\u30c9\u30d6\u30c3\u30af : \u6b63\u3057\u304f\u304d\u308c\u3044\u306a\u5b57\u3092\u66f8\u304f\u305f\u3081\u306e, \u7b2c4\u7248",
   "author": "\u6c5f\u5b88\u8ce2\u6cbb\u8457",
   "publisher": "\u4e09\u7701\u5802 2021/7",
   "isbn": "9784385200767",
   "holding": "\u4f53\u82b8 811.2-E54 \u4e00\u822c\u56f3\u66f8",
   "status": "\u914d\u67b6\u6e08",
   "imagesrc": ""
  }
 },
 {
  "index": 57,
  "data": {
   "link": "https://www.tulips.tsukuba.ac.jp/opac/volume/4034435?current=58&total=176&trans_url=%2Fopac%2Fsearch%3Farrivedwithin%3D1%26count%3D100%26defaultpage%3D1%26defaulttarget%3Dlocal%26order%3Darrival_date_d%26searchmode%3Dcomplex%26type%255B%255D%3Dbook",
   "title": "\u57fa\u790e\u304b\u3089\u5b66\u3076\u5b9f\u8a3c\u5206\u6790 : \u8a08\u91cf\u7d4c\u6e08\u5b66\u306e\u305f\u3081\u306e\u78ba\u7387\u3068\u7d71\u8a08",
   "author": "\u4e38\u8302\u5e78\u5e73\u8457",
   "publisher": "\u65b0\u4e16\u793e, \u30b5\u30a4\u30a8\u30f3\u30b9\u793e (\u767a\u58f2) 2021/9",
   "isbn": "9784883843336",
   "holding": "\u5927\u585a 331.19-Ma55 \u4e00\u822c\u56f3\u66f8",
   "status": "\u914d\u67b6\u6e08",
   "imagesrc": "https://books.google.com/books/content?id=inGXzgEACAAJ&printsec=frontcover&img=1&zoom=5"
  }
 },
 {
  "index": 58,
  "data": {
   "link": "https://www.tulips.tsukuba.ac.jp/opac/volume/4034541?current=59&total=176&trans_url=%2Fopac%2Fsearch%3Farrivedwithin%3D1%26count%3D100%26defaultpage%3D1%26defaulttarget%3Dlocal%26order%3Darrival_date_d%26searchmode%3Dcomplex%26type%255B%255D%3Dbook",
   "title": "\u5317\u306e\u88ab\u5dee\u5225\u306e\u4eba\u3005 : \u300c\u4e5e\u98df\u300d\u3068\u300c\u9769\u5e2b\u300d",
   "author": "\u6d6a\u5ddd\u5065\u6cbb\u8457",
   "publisher": "\u89e3\u653e\u51fa\u7248\u793e 2021/6",
   "isbn": "9784759242287",
   "holding": "\u4e2d\u592e 212.1-N47 \u4e00\u822c\u56f3\u66f8",
   "status": "\u914d\u67b6\u6e08",
   "imagesrc": "https://books.google.com/books/content?id=jQd_zgEACAAJ&printsec=frontcover&img=1&zoom=5"
  }
 },
 {
  "index": 59,
  "data": {
   "link": "https://www.tulips.tsukuba.ac.jp/opac/volume/4034419?current=60&total=176&trans_url=%2Fopac%2Fsearch%3Farrivedwithin%3D1%26count%3D100%26defaultpage%3D1%26defaulttarget%3Dlocal%26order%3Darrival_date_d%26searchmode%3Dcomplex%26type%255B%255D%3Dbook",
   "title": "\u898f\u7bc4\u3042\u3066\u306f\u3081\u5211\u4e8b\u8a34\u8a1f\u6cd5 : \u4e8b\u6848\u51e6\u7406\u306b\u5411\u3051\u305f\u624b\u7d9a\u6cd5\u306e\u89e3\u91c8",
   "author": "\u7c9f\u7530\u77e5\u7a42\u8457",
   "publisher": "\u7acb\u82b1\u66f8\u623f 2021/9",
   "isbn": "9784803724950",
   "holding": "\u5927\u585a 327.6-A97 \u4e00\u822c\u56f3\u66f8",
   "status": "\u914d\u67b6\u6e08",
   "imagesrc": "https://books.google.com/books/content?id=raajzgEACAAJ&printsec=frontcover&img=1&zoom=5"
  }
 },
 {
  "index": 60,
  "data": {
   "link": "https://www.tulips.tsukuba.ac.jp/opac/volume/4034492?current=61&total=176&trans_url=%2Fopac%2Fsearch%3Farrivedwithin%3D1%26count%3D100%26defaultpage%3D1%26defaulttarget%3Dlocal%26order%3Darrival_date_d%26searchmode%3Dcomplex%26type%255B%255D%3Dbook",
   "title": "\u30ae\u30e3\u30eb\u96fb\u3068\u3064\u304f\u308b!\u30d0\u30a4\u30d6\u30b9\u30c6\u30f3\u30a2\u30b2\u30b5\u30a4\u30d0\u30fc\u30d1\u30f3\u30af\u5149\u308a\u7269\u96fb\u5b50\u5de5\u4f5c",
   "author": "\u30ae\u30e3\u30eb\u96fb\u8457",
   "publisher": "\u30aa\u30fc\u30e0\u793e 2021/9",
   "isbn": "9784274227516",
   "holding": "\u56f3\u60c5\u642c\u9001\u4e2d 549-G99 \u4e00\u822c\u56f3\u66f8",
   "status": "\u914d\u67b6\u6e08",
   "imagesrc": "https://books.google.com/books/content?id=M-tBEAAAQBAJ&printsec=frontcover&img=1&zoom=5&edge=curl"
  }
 },
 {
  "index": 61,
  "data": {
   "link": "https://www.tulips.tsukuba.ac.jp/opac/volume/4034223?current=62&total=176&trans_url=%2Fopac%2Fsearch%3Farrivedwithin%3D1%26count%3D100%26defaultpage%3D1%26defaulttarget%3Dlocal%26order%3Darrival_date_d%26searchmode%3Dcomplex%26type%255B%255D%3Dbook",
   "title": "\u6559\u5e2b\u3068\u5b50\u3069\u3082\u306e\u305f\u3081\u306e\u4f53\u80b2\u306e\u300c\u6559\u79d1\u66f8\u300d : \u4e3b\u4f53\u7684\u30fb\u5bfe\u8a71\u7684\u3067\u6df1\u3044\u5b66\u3073\u3092\u3064\u304f\u308b! : \u5168\u9818\u57df\u306e\u5b66\u7fd2\u30d7\u30ea\u30f3\u30c8&\u5b66\u7fd2\u30ab\u30fc\u30c9\u3092\u53ce\u9332, \u4e2d\u5b66\u5e74",
   "author": "\u9234\u6728\u76f4\u6a39\u7de8\u8457/\u77f3\u4e95\u5353\u4e4b [\u307b\u304b] \u7de8\u96c6",
   "publisher": "\u660e\u6cbb\u56f3\u66f8\u51fa\u7248 2021/7",
   "isbn": "9784184382176",
   "holding": "\u4f53\u82b8 375.492-Su96 \u4e00\u822c\u56f3\u66f8",
   "status": "\u914d\u67b6\u6e08",
   "imagesrc": "https://books.google.com/books/content?id=2JmBzgEACAAJ&printsec=frontcover&img=1&zoom=5"
  }
 },
 {
  "index": 62,
  "data": {
   "link": "https://www.tulips.tsukuba.ac.jp/opac/volume/4034224?current=63&total=176&trans_url=%2Fopac%2Fsearch%3Farrivedwithin%3D1%26count%3D100%26defaultpage%3D1%26defaulttarget%3Dlocal%26order%3Darrival_date_d%26searchmode%3Dcomplex%26type%255B%255D%3Dbook",
   "title": "\u6559\u5e2b\u3068\u5b50\u3069\u3082\u306e\u305f\u3081\u306e\u4f53\u80b2\u306e\u300c\u6559\u79d1\u66f8\u300d : \u4e3b\u4f53\u7684\u30fb\u5bfe\u8a71\u7684\u3067\u6df1\u3044\u5b66\u3073\u3092\u3064\u304f\u308b! : \u5168\u9818\u57df\u306e\u5b66\u7fd2\u30d7\u30ea\u30f3\u30c8&\u5b66\u7fd2\u30ab\u30fc\u30c9\u3092\u53ce\u9332, \u4f4e\u5b66\u5e74",
   "author": "\u9234\u6728\u76f4\u6a39\u7de8\u8457/\u77f3\u4e95\u5353\u4e4b [\u307b\u304b] \u7de8\u96c6",
   "publisher": "\u660e\u6cbb\u56f3\u66f8\u51fa\u7248 2021/7",
   "isbn": "9784184381131",
   "holding": "\u4f53\u82b8 375.492-Su96 \u4e00\u822c\u56f3\u66f8",
   "status": "\u914d\u67b6\u6e08",
   "imagesrc": "https://books.google.com/books/content?id=5amBzgEACAAJ&printsec=frontcover&img=1&zoom=5"
  }
 },
 {
  "index": 63,
  "data": {
   "link": "https://www.tulips.tsukuba.ac.jp/opac/volume/4034412?current=64&total=176&trans_url=%2Fopac%2Fsearch%3Farrivedwithin%3D1%26count%3D100%26defaultpage%3D1%26defaulttarget%3Dlocal%26order%3Darrival_date_d%26searchmode%3Dcomplex%26type%255B%255D%3Dbook",
   "title": "\u5149\u5b66\u306e\u30a8\u30b9\u30ce\u30b0\u30e9\u30d5\u30a3 : \u30d5\u30a3\u30fc\u30eb\u30c9\u30ef\u30fc\u30af/\u6620\u753b\u6279\u8a55",
   "author": "\u91d1\u5b50\u904a\u8457",
   "publisher": "\u68ee\u8a71\u793e 2021/6",
   "isbn": "9784864051606",
   "holding": "\u4f53\u82b8 778.04-Ka53 \u4e00\u822c\u56f3\u66f8",
   "status": "\u914d\u67b6\u6e08",
   "imagesrc": "https://books.google.com/books/content?id=nLKBzgEACAAJ&printsec=frontcover&img=1&zoom=5"
  }
 },
 {
  "index": 64,
  "data": {
   "link": "https://www.tulips.tsukuba.ac.jp/opac/volume/4034543?current=65&total=176&trans_url=%2Fopac%2Fsearch%3Farrivedwithin%3D1%26count%3D100%26defaultpage%3D1%26defaulttarget%3Dlocal%26order%3Darrival_date_d%26searchmode%3Dcomplex%26type%255B%255D%3Dbook",
   "title": "\u9ad8\u7cbe\u5ea6\u6559\u80b2\u30d3\u30c3\u30b0\u30c7\u30fc\u30bf\u3067\u5909\u308f\u308b\u8a18\u61b6\u3068\u6559\u80b2\u306e\u5e38\u8b58 : \u30de\u30a4\u30af\u30ed\u30b9\u30c6\u30c3\u30d7\u30fb\u30b9\u30b1\u30b8\u30e5\u30fc\u30ea\u30f3\u30b0\u306b\u3088\u308b\u77e5\u8b58\u7fd2\u5f97\u306e\u52b9\u7387\u5316",
   "author": "\u5bfa\u6fa4\u5b5d\u6587\u7de8\u8457",
   "publisher": "\u98a8\u9593\u66f8\u623f 2021/3",
   "isbn": "9784759923803",
   "holding": "\u4e2d\u592e 371.7-Te62 \u4e00\u822c\u56f3\u66f8",
   "status": "\u914d\u67b6\u6e08",
   "imagesrc": "https://books.google.com/books/content?id=u85kzgEACAAJ&printsec=frontcover&img=1&zoom=5"
  }
 },
 {
  "index": 65,
  "data": {
   "link": "https://www.tulips.tsukuba.ac.jp/opac/volume/4034507?current=66&total=176&trans_url=%2Fopac%2Fsearch%3Farrivedwithin%3D1%26count%3D100%26defaultpage%3D1%26defaulttarget%3Dlocal%26order%3Darrival_date_d%26searchmode%3Dcomplex%26type%255B%255D%3Dbook",
   "title": "\u30b3\u30f3\u30d1\u30a4\u30e9 : \u539f\u7406\u3068\u69cb\u9020",
   "author": "\u5927\u5800\u6df3\u8457",
   "publisher": "\u5171\u7acb\u51fa\u7248 2021/9",
   "isbn": "9784320124783",
   "holding": "\u56f3\u60c5\u642c\u9001\u4e2d 007.64-O29 \u4e00\u822c\u56f3\u66f8",
   "status": "\u914d\u67b6\u6e08",
   "imagesrc": "https://books.google.com/books/content?id=2diNzgEACAAJ&printsec=frontcover&img=1&zoom=5"
  }
 },
 {
  "index": 66,
  "data": {
   "link": "https://www.tulips.tsukuba.ac.jp/opac/volume/4034509?current=67&total=176&trans_url=%2Fopac%2Fsearch%3Farrivedwithin%3D1%26count%3D100%26defaultpage%3D1%26defaulttarget%3Dlocal%26order%3Darrival_date_d%26searchmode%3Dcomplex%26type%255B%255D%3Dbook",
   "title": "\u30b3\u30f3\u30d4\u30e5\u30fc\u30bf\u306e\u3057\u304f\u307f : \u60c5\u5831\u6d3b\u7528\u80fd\u529b\u3068\u306f\u4f55\u304b\u3092\u8003\u3048\u308b",
   "author": "\u4f50\u85e4\u4e00\u90ce\u8457",
   "publisher": "\u30b5\u30a4\u30a8\u30f3\u30b9\u793e 2021/9",
   "isbn": "9784781915142",
   "holding": "\u56f3\u60c5\u642c\u9001\u4e2d 007.6-Sa85 \u4e00\u822c\u56f3\u66f8",
   "status": "\u914d\u67b6\u6e08",
   "imagesrc": "https://books.google.com/books/content?id=t3WZzgEACAAJ&printsec=frontcover&img=1&zoom=5"
  }
 },
 {
  "index": 67,
  "data": {
   "link": "https://www.tulips.tsukuba.ac.jp/opac/volume/4034432?current=68&total=176&trans_url=%2Fopac%2Fsearch%3Farrivedwithin%3D1%26count%3D100%26defaultpage%3D1%26defaulttarget%3Dlocal%26order%3Darrival_date_d%26searchmode%3Dcomplex%26type%255B%255D%3Dbook",
   "title": "\u50b5\u6a29\u6cd5\u6539\u6b63\u3068\u5224\u4f8b\u306e\u884c\u65b9 : \u65b0\u3057\u3044\u6c11\u6cd5\u306b\u304a\u3051\u308b\u5224\u4f8b\u306e\u610f\u7fa9\u306e\u691c\u8a3c",
   "author": "\u79cb\u5c71\u9756\u6d69, \u4f0a\u85e4\u6804\u5bff, \u5bae\u4e0b\u4fee\u4e00\u7de8\u8457",
   "publisher": "\u65e5\u672c\u8a55\u8ad6\u793e 2021/9",
   "isbn": "9784535525771",
   "holding": "\u5927\u585a 324.4-A38 \u4e00\u822c\u56f3\u66f8",
   "status": "\u914d\u67b6\u6e08",
   "imagesrc": "https://books.google.com/books/content?id=Re6OzgEACAAJ&printsec=frontcover&img=1&zoom=5"
  }
 },
 {
  "index": 68,
  "data": {
   "link": "https://www.tulips.tsukuba.ac.jp/opac/volume/4034430?current=69&total=176&trans_url=%2Fopac%2Fsearch%3Farrivedwithin%3D1%26count%3D100%26defaultpage%3D1%26defaulttarget%3Dlocal%26order%3Darrival_date_d%26searchmode%3Dcomplex%26type%255B%255D%3Dbook",
   "title": "\u6700\u65b0\u91cd\u8981\u5224\u4f8b\u89e3\u8aac\u6c11\u4e8b\u8a34\u8a1f\u6cd5",
   "author": "\u5c0f\u6797\u79c0\u4e4b, \u5c71\u672c\u6d69\u7f8e\u8457",
   "publisher": "\u65e5\u672c\u8a55\u8ad6\u793e 2021/9",
   "isbn": "9784535525962",
   "holding": "\u5927\u585a 327.2-Ko12 \u4e00\u822c\u56f3\u66f8",
   "status": "\u914d\u67b6\u6e08",
   "imagesrc": "https://books.google.com/books/content?id=SHOPzgEACAAJ&printsec=frontcover&img=1&zoom=5"
  }
 },
 {
  "index": 69,
  "data": {
   "link": "https://www.tulips.tsukuba.ac.jp/opac/volume/4034513?current=70&total=176&trans_url=%2Fopac%2Fsearch%3Farrivedwithin%3D1%26count%3D100%26defaultpage%3D1%26defaulttarget%3Dlocal%26order%3Darrival_date_d%26searchmode%3Dcomplex%26type%255B%255D%3Dbook",
   "title": "\u6700\u77ed\u30b3\u30fc\u30b9\u3067\u308f\u304b\u308bPyTorch & \u6df1\u5c64\u5b66\u7fd2 (\u30c7\u30a3\u30fc\u30d7\u30e9\u30fc\u30cb\u30f3\u30b0) \u30d7\u30ed\u30b0\u30e9\u30df\u30f3\u30b0",
   "author": "\u8d64\u77f3\u96c5\u5178\u8457",
   "publisher": "\u65e5\u7d4cBP, \u65e5\u7d4cBP\u30de\u30fc\u30b1\u30c6\u30a3\u30f3\u30b0 (\u767a\u58f2) 2021/9",
   "isbn": "9784296110322",
   "holding": "\u56f3\u60c5\u642c\u9001\u4e2d 007.13-A29 \u4e00\u822c\u56f3\u66f8",
   "status": "\u914d\u67b6\u6e08",
   "imagesrc": "https://books.google.com/books/content?id=k36dzgEACAAJ&printsec=frontcover&img=1&zoom=5"
  }
 },
 {
  "index": 70,
  "data": {
   "link": "https://www.tulips.tsukuba.ac.jp/opac/volume/4034213?current=71&total=176&trans_url=%2Fopac%2Fsearch%3Farrivedwithin%3D1%26count%3D100%26defaultpage%3D1%26defaulttarget%3Dlocal%26order%3Darrival_date_d%26searchmode%3Dcomplex%26type%255B%255D%3Dbook",
   "title": "\u81ea\u5728\u5316\u8eab\u4f53\u8ad6 : \u8d85\u611f\u899a\u30fb\u8d85\u8eab\u4f53\u30fb\u5909\u8eab\u30fb\u5206\u8eab\u30fb\u5408\u4f53\u304c\u7e54\u308a\u306a\u3059\u4eba\u985e\u306e\u672a\u6765",
   "author": "\u7a32\u898b\u660c\u5f66 [\u307b\u304b] \u8457",
   "publisher": "\u30a8\u30cc\u30fb\u30c6\u30a3\u30fc\u30fb\u30a8\u30b9 2021/2",
   "isbn": "9784860436858",
   "holding": "\u4e2d\u592e 007.3-I53 \u4e00\u822c\u56f3\u66f8",
   "status": "\u914d\u67b6\u6e08",
   "imagesrc": "https://books.google.com/books/content?id=OpwtEAAAQBAJ&printsec=frontcover&img=1&zoom=5&edge=curl"
  }
 },
 {
  "index": 71,
  "data": {
   "link": "https://www.tulips.tsukuba.ac.jp/opac/volume/4034495?current=72&total=176&trans_url=%2Fopac%2Fsearch%3Farrivedwithin%3D1%26count%3D100%26defaultpage%3D1%26defaulttarget%3Dlocal%26order%3Darrival_date_d%26searchmode%3Dcomplex%26type%255B%255D%3Dbook",
   "title": "\u5b9f\u8df5\u6642\u7cfb\u5217\u89e3\u6790 : \u7d71\u8a08\u3068\u6a5f\u68b0\u5b66\u7fd2\u306b\u3088\u308b\u4e88\u6e2c",
   "author": "Aileen Nielsen\u8457/\u5c71\u5d0e\u90a6\u5b50, \u5c71\u5d0e\u5eb7\u5b8f\u8a33",
   "publisher": "\u30aa\u30e9\u30a4\u30ea\u30fc\u30fb\u30b8\u30e3\u30d1\u30f3, \u30aa\u30fc\u30e0\u793e (\u767a\u58f2) 2021/9",
   "isbn": "9784873119601",
   "holding": "\u56f3\u60c5\u642c\u9001\u4e2d 417.6-N71 \u4e00\u822c\u56f3\u66f8",
   "status": "\u914d\u67b6\u6e08",
   "imagesrc": "https://books.google.com/books/content?id=AI2SzgEACAAJ&printsec=frontcover&img=1&zoom=5"
  }
 },
 {
  "index": 72,
  "data": {
   "link": "https://www.tulips.tsukuba.ac.jp/opac/volume/4034459?current=73&total=176&trans_url=%2Fopac%2Fsearch%3Farrivedwithin%3D1%26count%3D100%26defaultpage%3D1%26defaulttarget%3Dlocal%26order%3Darrival_date_d%26searchmode%3Dcomplex%26type%255B%255D%3Dbook",
   "title": "\u3057\u306a\u3084\u304b\u306a\u5efa\u7bc9",
   "author": "\u5357\u4e00\u8aa0\u8457",
   "publisher": "\u7dcf\u5408\u8cc7\u683c 2021/5",
   "isbn": "9784864174022",
   "holding": "\u4f53\u82b8 520-Mi37 \u4e00\u822c\u56f3\u66f8",
   "status": "\u914d\u67b6\u6e08",
   "imagesrc": "https://books.google.com/books/content?id=t2aKzgEACAAJ&printsec=frontcover&img=1&zoom=5"
  }
 },
 {
  "index": 73,
  "data": {
   "link": "https://www.tulips.tsukuba.ac.jp/opac/volume/4034151?current=74&total=176&trans_url=%2Fopac%2Fsearch%3Farrivedwithin%3D1%26count%3D100%26defaultpage%3D1%26defaulttarget%3Dlocal%26order%3Darrival_date_d%26searchmode%3Dcomplex%26type%255B%255D%3Dbook",
   "title": "\u65b0\u5b66\u7fd2\u6307\u5c0e\u8981\u9818\u306b\u793a\u3055\u308c\u308b\u8074\u899a\u969c\u5bb3\u306e\u72b6\u614b\u7b49\u306b\u5fdc\u3058\u305f\u8a00\u8a9e\u6d3b\u52d5\u306e\u5145\u5b9f : \u4eba\u5de5\u5185\u8033\u88c5\u7528\u5150\u306b\u5bfe\u3059\u308b\u5168\u56fd\u8abf\u67fb\u3068\u5b9f\u8df5\u7814\u7a76\u306b\u57fa\u3065\u3044\u3066",
   "author": "\u912d\u4ec1\u8c6a\u7814\u7a76\u4ee3\u8868",
   "publisher": "\u912d\u4ec1\u8c6a 2021/3",
   "isbn": "",
   "holding": "\u4e2d\u592e 378.2-Te21 \u4e00\u822c\u56f3\u66f8, \u4e2d\u592e\u672c\u5b66 378.2-Te21 \u672c\u5b66",
   "status": "\u914d\u67b6\u6e08",
   "imagesrc": ""
  }
 },
 {
  "index": 74,
  "data": {
   "link": "https://www.tulips.tsukuba.ac.jp/opac/volume/4034506?current=75&total=176&trans_url=%2Fopac%2Fsearch%3Farrivedwithin%3D1%26count%3D100%26defaultpage%3D1%26defaulttarget%3Dlocal%26order%3Darrival_date_d%26searchmode%3Dcomplex%26type%255B%255D%3Dbook",
   "title": "\u65b0\u30fb\u660e\u89e3C\u8a00\u8a9e, \u5165\u9580\u7de8, \u7b2c2\u7248",
   "author": "\u67f4\u7530\u671b\u6d0b\u8457",
   "publisher": "SB\u30af\u30ea\u30a8\u30a4\u30c6\u30a3\u30d6 2021/9",
   "isbn": "9784815609795",
   "holding": "\u56f3\u60c5\u642c\u9001\u4e2d 007.64-Sh18 \u4e00\u822c\u56f3\u66f8",
   "status": "\u914d\u67b6\u6e08",
   "imagesrc": "https://books.google.com/books/content?id=7l5BEAAAQBAJ&printsec=frontcover&img=1&zoom=5&edge=curl"
  }
 },
 {
  "index": 75,
  "data": {
   "link": "https://www.tulips.tsukuba.ac.jp/opac/volume/4034438?current=76&total=176&trans_url=%2Fopac%2Fsearch%3Farrivedwithin%3D1%26count%3D100%26defaultpage%3D1%26defaulttarget%3Dlocal%26order%3Darrival_date_d%26searchmode%3Dcomplex%26type%255B%255D%3Dbook",
   "title": "\u5fc3\u7406\u5b66\u7814\u7a76\u6cd5 : progress & application, \u7b2c2\u7248",
   "author": "\u6751\u4e95\u6f64\u4e00\u90ce\u7de8\u8457",
   "publisher": "\u30b5\u30a4\u30a8\u30f3\u30b9\u793e 2021/9",
   "isbn": "9784781915098",
   "holding": "\u5927\u585a 140.7-Mu41 \u4e00\u822c\u56f3\u66f8",
   "status": "\u914d\u67b6\u6e08",
   "imagesrc": "https://books.google.com/books/content?id=xp2YzgEACAAJ&printsec=frontcover&img=1&zoom=5"
  }
 },
 {
  "index": 76,
  "data": {
   "link": "https://www.tulips.tsukuba.ac.jp/opac/volume/4034209?current=77&total=176&trans_url=%2Fopac%2Fsearch%3Farrivedwithin%3D1%26count%3D100%26defaultpage%3D1%26defaulttarget%3Dlocal%26order%3Darrival_date_d%26searchmode%3Dcomplex%26type%255B%255D%3Dbook",
   "title": "\u30b9\u30e9\u30d0\u30e4 : \u6771\u5357\u30a2\u30b8\u30a2\u90fd\u5e02\u306e\u8d77\u6e90\u30fb\u5f62\u6210\u30fb\u5909\u5bb9\u30fb\u8ee2\u6210 : \u30b3\u30b9\u30e2\u30b9\u3068\u3057\u3066\u306e\u30ab\u30f3\u30dd\u30f3",
   "author": "\u5e03\u91ce\u4fee\u53f8\u8457",
   "publisher": "\u4eac\u90fd\u5927\u5b66\u5b66\u8853\u51fa\u7248\u4f1a 2021/2",
   "isbn": "9784814003198",
   "holding": "\u4e2d\u592e 518.8-F89 \u4e00\u822c\u56f3\u66f8",
   "status": "\u914d\u67b6\u6e08",
   "imagesrc": "https://books.google.com/books/content?id=sU9DzgEACAAJ&printsec=frontcover&img=1&zoom=5"
  }
 },
 {
  "index": 77,
  "data": {
   "link": "https://www.tulips.tsukuba.ac.jp/opac/volume/4034488?current=78&total=176&trans_url=%2Fopac%2Fsearch%3Farrivedwithin%3D1%26count%3D100%26defaultpage%3D1%26defaulttarget%3Dlocal%26order%3Darrival_date_d%26searchmode%3Dcomplex%26type%255B%255D%3Dbook",
   "title": "\u30bb\u30ad\u30e5\u30a2\u30fb\u30d0\u30a4\u30fb\u30c7\u30b6\u30a4\u30f3 : \u5b89\u5168\u306a\u30bd\u30d5\u30c8\u30a6\u30a7\u30a2\u8a2d\u8a08",
   "author": "Dan Bergh Johnsson, Daniel Deogun, Daniel Sawano\u8457/\u9808\u7530\u667a\u4e4b\u8a33",
   "publisher": "\u30de\u30a4\u30ca\u30d3\u51fa\u7248 2021/9",
   "isbn": "9784839975999",
   "holding": "\u56f3\u60c5\u642c\u9001\u4e2d 007.63-J64 \u4e00\u822c\u56f3\u66f8",
   "status": "\u914d\u67b6\u6e08",
   "imagesrc": "https://books.google.com/books/content?id=ZHaWzgEACAAJ&printsec=frontcover&img=1&zoom=5"
  }
 },
 {
  "index": 78,
  "data": {
   "link": "https://www.tulips.tsukuba.ac.jp/opac/volume/4034498?current=79&total=176&trans_url=%2Fopac%2Fsearch%3Farrivedwithin%3D1%26count%3D100%26defaultpage%3D1%26defaulttarget%3Dlocal%26order%3Darrival_date_d%26searchmode%3Dcomplex%26type%255B%255D%3Dbook",
   "title": "\u30bd\u30d5\u30c8\u30ae\u30e0\u30cb\u30af\u3092\u4f7f\u3063\u305f\u697d\u3057\u3044\u904b\u52d5\u904a\u3073 : \u30dc\u30fc\u30eb\u904a\u3073\u306e\u5c0e\u5165\u306b",
   "author": "",
   "publisher": "\u65e5\u672cG\u30dc\u30fc\u30eb\u5354\u4f1a 20??",
   "isbn": "",
   "holding": "\u4f53\u82b8 781-So24 \u4e00\u822c\u56f3\u66f8",
   "status": "\u914d\u67b6\u6e08",
   "imagesrc": ""
  }
 },
 {
  "index": 79,
  "data": {
   "link": "https://www.tulips.tsukuba.ac.jp/opac/volume/4034475?current=80&total=176&trans_url=%2Fopac%2Fsearch%3Farrivedwithin%3D1%26count%3D100%26defaultpage%3D1%26defaulttarget%3Dlocal%26order%3Darrival_date_d%26searchmode%3Dcomplex%26type%255B%255D%3Dbook",
   "title": "\u4e2d\u5b66\u6821\u7f8e\u8853\u30c6\u30c3\u30d1\u30f3\u984c\u6750\u30e2\u30c7\u30eb : \u65b0\u5b66\u7fd2\u6307\u5c0e\u8981\u9818\u5bfe\u5fdc : \u6307\u5c0e\u304b\u3089\u8a55\u4fa1\u307e\u3067\u3059\u3079\u3066\u304c\u5206\u304b\u308b!, \u7b2c2\u30fb3\u5b66\u5e74",
   "author": "\u4e09\u6d66\u82f1\u751f, \u5b89\u85e4\u771e\u6a39\u7de8\u8457/\u611b\u77e5\u770c\u9020\u5f62\u6559\u80b2\u7814\u7a76\u4f1a\u8457",
   "publisher": "\u660e\u6cbb\u56f3\u66f8\u51fa\u7248 2021/7",
   "isbn": "9784183562142",
   "holding": "\u4f53\u82b8 375.72-N37-2/3 \u4e00\u822c\u56f3\u66f8",
   "status": "\u914d\u67b6\u6e08",
   "imagesrc": "https://books.google.com/books/content?id=IqGLzgEACAAJ&printsec=frontcover&img=1&zoom=5"
  }
 },
 {
  "index": 80,
  "data": {
   "link": "https://www.tulips.tsukuba.ac.jp/opac/volume/4034441?current=81&total=176&trans_url=%2Fopac%2Fsearch%3Farrivedwithin%3D1%26count%3D100%26defaultpage%3D1%26defaulttarget%3Dlocal%26order%3Darrival_date_d%26searchmode%3Dcomplex%26type%255B%255D%3Dbook",
   "title": "\u5e1d\u56fd\u65e5\u672c\u306e\u7d71\u6cbb\u6cd5 : \u5185\u5730\u3068\u690d\u6c11\u5730\u671d\u9bae\u30fb\u53f0\u6e7e\u306e\u5730\u65b9\u5236\u5ea6\u3092\u7126\u70b9\u3068\u3059\u308b",
   "author": "\u5c71\u4e2d\u6c38\u4e4b\u4f51\u8457",
   "publisher": "\u5927\u962a\u5927\u5b66\u51fa\u7248\u4f1a 2021/3",
   "isbn": "9784872596762",
   "holding": "\u4e2d\u592e 317.8-Y34 \u4e00\u822c\u56f3\u66f8",
   "status": "\u914d\u67b6\u6e08",
   "imagesrc": "https://books.google.com/books/content?id=FDJpzgEACAAJ&printsec=frontcover&img=1&zoom=5"
  }
 },
 {
  "index": 81,
  "data": {
   "link": "https://www.tulips.tsukuba.ac.jp/opac/volume/4020992?current=82&total=176&trans_url=%2Fopac%2Fsearch%3Farrivedwithin%3D1%26count%3D100%26defaultpage%3D1%26defaulttarget%3Dlocal%26order%3Darrival_date_d%26searchmode%3Dcomplex%26type%255B%255D%3Dbook",
   "title": "\u30c7\u30fc\u30bf\u79d1\u5b66\u306e\u305f\u3081\u306e\u5fae\u5206\u7a4d\u5206\u30fb\u7dda\u5f62\u4ee3\u6570 : MATLAB\u3067\u4f53\u9a13\u3059\u308b\u6570\u5b66\u57fa\u790e",
   "author": "\u85e4\u539f\u6bc5\u592b, \u85e4\u5802\u771e\u6cbb\u8457",
   "publisher": "\u6771\u4eac\u5927\u5b66\u51fa\u7248\u4f1a 2021/8",
   "isbn": "9784130624626",
   "holding": "\u4e2d\u592e 413.3-F68 \u4e00\u822c\u56f3\u66f8, \u56f3\u60c5\u642c\u9001\u4e2d 413.3-F68 \u4e00\u822c\u56f3\u66f8",
   "status": "\u914d\u67b6\u6e08",
   "imagesrc": "https://books.google.com/books/content?id=qBSMzgEACAAJ&printsec=frontcover&img=1&zoom=5"
  }
 },
 {
  "index": 82,
  "data": {
   "link": "https://www.tulips.tsukuba.ac.jp/opac/volume/4034529?current=83&total=176&trans_url=%2Fopac%2Fsearch%3Farrivedwithin%3D1%26count%3D100%26defaultpage%3D1%26defaulttarget%3Dlocal%26order%3Darrival_date_d%26searchmode%3Dcomplex%26type%255B%255D%3Dbook",
   "title": "\u30c9\u30ac\u30c0\u30f3\u30b9\u30c7\u30c3\u30b5\u30f3",
   "author": "\u30dd\u30fc\u30eb\u30fb\u30f4\u30a1\u30ec\u30ea\u30fc\u8457/\u585a\u672c\u660c\u5247\u8a33",
   "publisher": "\u5ca9\u6ce2\u66f8\u5e97 2021/11",
   "isbn": "9784003256060",
   "holding": "\u4e2d\u592e 081-I95-R560-6 \u4e00\u822c\u56f3\u66f8, \u4f53\u82b8 081-I95-R560-6 \u4e00\u822c\u56f3\u66f8, \u533b\u5b66 081-I95-R560-6 \u4e00\u822c\u56f3\u66f8",
   "status": "\u914d\u67b6\u6e08",
   "imagesrc": "https://books.google.com/books/content?id=kU-wzgEACAAJ&printsec=frontcover&img=1&zoom=5"
  }
 },
 {
  "index": 83,
  "data": {
   "link": "https://www.tulips.tsukuba.ac.jp/opac/volume/1957784?current=84&total=176&trans_url=%2Fopac%2Fsearch%3Farrivedwithin%3D1%26count%3D100%26defaultpage%3D1%26defaulttarget%3Dlocal%26order%3Darrival_date_d%26searchmode%3Dcomplex%26type%255B%255D%3Dbook",
   "title": "\u65e5\u82f1\u5bfe\u7167 : \u82f1\u8a9e\u5b66\u306e\u57fa\u790e",
   "author": "\u4e09\u539f\u5065\u4e00, \u9ad8\u898b\u5065\u4e00\u7de8\u8457/\u7aaa\u8597\u6674\u592b [\u307b\u304b] \u8457",
   "publisher": "\u304f\u308d\u3057\u304a\u51fa\u7248 2013/11",
   "isbn": "9784874246009",
   "holding": "\u4e2d\u592e 830.1-Mi17 \u4e00\u822c\u56f3\u66f8",
   "status": "\u914d\u67b6\u6e08",
   "imagesrc": "https://books.google.com/books/content?id=GIgpngEACAAJ&printsec=frontcover&img=1&zoom=5"
  }
 },
 {
  "index": 84,
  "data": {
   "link": "https://www.tulips.tsukuba.ac.jp/opac/volume/4002079?current=85&total=176&trans_url=%2Fopac%2Fsearch%3Farrivedwithin%3D1%26count%3D100%26defaultpage%3D1%26defaulttarget%3Dlocal%26order%3Darrival_date_d%26searchmode%3Dcomplex%26type%255B%255D%3Dbook",
   "title": "\u65e5\u672c\u306e\u30b9\u30dd\u30fc\u30c4\u3068\u6cd5\u30fb\u30ac\u30d0\u30ca\u30f3\u30b9",
   "author": "\u4e95\u4e0a\u5178\u4e4b\u8457",
   "publisher": "\u4fe1\u5c71\u793e 2021/6",
   "isbn": "9784797281064",
   "holding": "\u4f53\u82b8 780-I57-1 \u4e00\u822c\u56f3\u66f8, \u5927\u585a 780-I57-1 \u4e00\u822c\u56f3\u66f8",
   "status": "\u914d\u67b6\u6e08",
   "imagesrc": ""
  }
 },
 {
  "index": 85,
  "data": {
   "link": "https://www.tulips.tsukuba.ac.jp/opac/volume/4034517?current=86&total=176&trans_url=%2Fopac%2Fsearch%3Farrivedwithin%3D1%26count%3D100%26defaultpage%3D1%26defaulttarget%3Dlocal%26order%3Darrival_date_d%26searchmode%3Dcomplex%26type%255B%255D%3Dbook",
   "title": "\u5165\u9580\u6a5f\u68b0\u5b66\u7fd2\u30d1\u30a4\u30d7\u30e9\u30a4\u30f3 : TensorFlow\u3067\u5b66\u3076\u30ef\u30fc\u30af\u30d5\u30ed\u30fc\u306e\u81ea\u52d5\u5316",
   "author": "Hannes Hapke, Catherine Nelson\u8457/\u4e2d\u5c71\u5149\u6a39\u8a33",
   "publisher": "\u30aa\u30e9\u30a4\u30ea\u30fc\u30fb\u30b8\u30e3\u30d1\u30f3, \u30aa\u30fc\u30e0\u793e (\u767a\u58f2) 2021/9",
   "isbn": "9784873119519",
   "holding": "\u56f3\u60c5\u642c\u9001\u4e2d 007.13-H29 \u4e00\u822c\u56f3\u66f8",
   "status": "\u914d\u67b6\u6e08",
   "imagesrc": "https://books.google.com/books/content?id=l-2TzgEACAAJ&printsec=frontcover&img=1&zoom=5"
  }
 },
 {
  "index": 86,
  "data": {
   "link": "https://www.tulips.tsukuba.ac.jp/opac/volume/4034497?current=87&total=176&trans_url=%2Fopac%2Fsearch%3Farrivedwithin%3D1%26count%3D100%26defaultpage%3D1%26defaulttarget%3Dlocal%26order%3Darrival_date_d%26searchmode%3Dcomplex%26type%255B%255D%3Dbook",
   "title": "\u306f\u3058\u3081\u3066\u306ePower Automate Desktop : \u7121\u6599&\u30ce\u30fc\u30b3\u30fc\u30c9RPA\u3067\u306f\u3058\u3081\u308b\u696d\u52d9\u81ea\u52d5\u5316",
   "author": "ASAHI Accounting Robot\u7814\u7a76\u6240\u8457",
   "publisher": "\u6280\u8853\u8a55\u8ad6\u793e 2021/10",
   "isbn": "9784297123116",
   "holding": "\u56f3\u60c5\u642c\u9001\u4e2d 336.57-A11 \u4e00\u822c\u56f3\u66f8",
   "status": "\u914d\u67b6\u6e08",
   "imagesrc": "https://books.google.com/books/content?id=jOmRzgEACAAJ&printsec=frontcover&img=1&zoom=5"
  }
 },
 {
  "index": 87,
  "data": {
   "link": "https://www.tulips.tsukuba.ac.jp/opac/volume/4034530?current=88&total=176&trans_url=%2Fopac%2Fsearch%3Farrivedwithin%3D1%26count%3D100%26defaultpage%3D1%26defaulttarget%3Dlocal%26order%3Darrival_date_d%26searchmode%3Dcomplex%26type%255B%255D%3Dbook",
   "title": "\u53cd\u5553\u8499\u601d\u60f3 : \u4ed6\u4e8c\u7bc7",
   "author": "\u30d0\u30fc\u30ea\u30f3\u8457/edited by Henry Hardy/\u677e\u672c\u793c\u4e8c\u7de8",
   "publisher": "\u5ca9\u6ce2\u66f8\u5e97 2021/11",
   "isbn": "9784003368428",
   "holding": "\u533b\u5b66 081-I95-B684-2 \u4e00\u822c\u56f3\u66f8, \u4f53\u82b8 081-I95-B684-2 \u4e00\u822c\u56f3\u66f8, \u4e2d\u592e 081-I95-B684-2 \u4e00\u822c\u56f3\u66f8",
   "status": "\u914d\u67b6\u6e08",
   "imagesrc": "https://books.google.com/books/content?id=XkqzzgEACAAJ&printsec=frontcover&img=1&zoom=5"
  }
 },
 {
  "index": 88,
  "data": {
   "link": "https://www.tulips.tsukuba.ac.jp/opac/volume/4034428?current=89&total=176&trans_url=%2Fopac%2Fsearch%3Farrivedwithin%3D1%26count%3D100%26defaultpage%3D1%26defaulttarget%3Dlocal%26order%3Darrival_date_d%26searchmode%3Dcomplex%26type%255B%255D%3Dbook",
   "title": "\u5224\u4f8b\u6c11\u4e8b\u8a34\u8a1f\u6cd5\u5165\u9580",
   "author": "\u5ddd\u5d8b\u56db\u90ce\u7de8\u8457/\u5ddd\u5d8b\u56db\u90ce [\u307b\u304b\u8457]",
   "publisher": "\u65e5\u672c\u8a55\u8ad6\u793e 2021/9",
   "isbn": "9784535524361",
   "holding": "\u5927\u585a 327.2-Ka97 \u4e00\u822c\u56f3\u66f8",
   "status": "\u914d\u67b6\u6e08",
   "imagesrc": "https://books.google.com/books/content?id=if6OzgEACAAJ&printsec=frontcover&img=1&zoom=5"
  }
 },
 {
  "index": 89,
  "data": {
   "link": "https://www.tulips.tsukuba.ac.jp/opac/volume/4034540?current=90&total=176&trans_url=%2Fopac%2Fsearch%3Farrivedwithin%3D1%26count%3D100%26defaultpage%3D1%26defaulttarget%3Dlocal%26order%3Darrival_date_d%26searchmode%3Dcomplex%26type%255B%255D%3Dbook",
   "title": "\u6771\u30a2\u30b8\u30a2\u4ecf\u50cf\u53f2\u8ad6",
   "author": "\u85e4\u5ca1\u7a63\u8457",
   "publisher": "\u4e2d\u592e\u516c\u8ad6\u7f8e\u8853\u51fa\u7248 2021/7",
   "isbn": "9784805508930",
   "holding": "\u4f53\u82b8 718.021-F65 \u4e00\u822c\u56f3\u66f8",
   "status": "\u914d\u67b6\u6e08",
   "imagesrc": "https://books.google.com/books/content?id=vlCLzgEACAAJ&printsec=frontcover&img=1&zoom=5"
  }
 },
 {
  "index": 90,
  "data": {
   "link": "https://www.tulips.tsukuba.ac.jp/opac/volume/4034468?current=91&total=176&trans_url=%2Fopac%2Fsearch%3Farrivedwithin%3D1%26count%3D100%26defaultpage%3D1%26defaulttarget%3Dlocal%26order%3Darrival_date_d%26searchmode%3Dcomplex%26type%255B%255D%3Dbook",
   "title": "\u7f8e\u8853\u6279\u8a55\u96c6\u6210 : \u4e00\u4e5d\u4e94\u4e94-\u4e00\u4e5d\u516d\u56db",
   "author": "\u718a\u8c37\u4f0a\u4f50\u5b50 [\u307b\u304b] \u7de8\u8457",
   "publisher": "\u85dd\u83ef\u66f8\u9662 2021/6",
   "isbn": "9784904706091",
   "holding": "\u4f53\u82b8 702.16-Ku33 \u4e00\u822c\u56f3\u66f8",
   "status": "\u914d\u67b6\u6e08",
   "imagesrc": "https://books.google.com/books/content?id=AKyHzgEACAAJ&printsec=frontcover&img=1&zoom=5"
  }
 },
 {
  "index": 91,
  "data": {
   "link": "https://www.tulips.tsukuba.ac.jp/opac/volume/4034514?current=92&total=176&trans_url=%2Fopac%2Fsearch%3Farrivedwithin%3D1%26count%3D100%26defaultpage%3D1%26defaulttarget%3Dlocal%26order%3Darrival_date_d%26searchmode%3Dcomplex%26type%255B%255D%3Dbook",
   "title": "\u7269\u4f53\u691c\u51fa\u3068GAN\u3001\u30aa\u30fc\u30c8\u30a8\u30f3\u30b3\u30fc\u30c0\u30fc\u3001\u753b\u50cf\u51e6\u7406\u5165\u9580 : PyTorch/TensorFlow2\u306b\u3088\u308b\u767a\u5c55\u7684\u30fb\u5b9f\u88c5\u30c7\u30a3\u30fc\u30d7\u30e9\u30fc\u30cb\u30f3\u30b0",
   "author": "\u30c1\u30fc\u30e0\u30fb\u30ab\u30eb\u30dd\u8457",
   "publisher": "\u79c0\u548c\u30b7\u30b9\u30c6\u30e0 2021/9",
   "isbn": "9784798064642",
   "holding": "\u56f3\u60c5\u642c\u9001\u4e2d 007.1-C45 \u4e00\u822c\u56f3\u66f8",
   "status": "\u914d\u67b6\u6e08",
   "imagesrc": "https://books.google.com/books/content?id=kNRMEAAAQBAJ&printsec=frontcover&img=1&zoom=5&edge=curl"
  }
 },
 {
  "index": 92,
  "data": {
   "link": "https://www.tulips.tsukuba.ac.jp/opac/volume/4034546?current=93&total=176&trans_url=%2Fopac%2Fsearch%3Farrivedwithin%3D1%26count%3D100%26defaultpage%3D1%26defaulttarget%3Dlocal%26order%3Darrival_date_d%26searchmode%3Dcomplex%26type%255B%255D%3Dbook",
   "title": "\u300c\u6cd5\u3068\u7d4c\u6e08\u5b66\u300d\u306e\u63fa\u7c43",
   "author": "\u83ca\u5730\u8ad2\u8457",
   "publisher": "\u6210\u6587\u5802 2021/3",
   "isbn": "9784792306885",
   "holding": "\u4e2d\u592e 321-Ki24 \u4e00\u822c\u56f3\u66f8",
   "status": "\u914d\u67b6\u6e08",
   "imagesrc": "https://books.google.com/books/content?id=A3dlzgEACAAJ&printsec=frontcover&img=1&zoom=5"
  }
 },
 {
  "index": 93,
  "data": {
   "link": "https://www.tulips.tsukuba.ac.jp/opac/volume/4034531?current=94&total=176&trans_url=%2Fopac%2Fsearch%3Farrivedwithin%3D1%26count%3D100%26defaultpage%3D1%26defaulttarget%3Dlocal%26order%3Darrival_date_d%26searchmode%3Dcomplex%26type%255B%255D%3Dbook",
   "title": "\u30dc\u30fc\u30eb\u30b1\u30a2 : \u304a\u3046\u3061\u3067\u3001\u7c21\u5358\u3001\u6c17\u6301\u3061\u3044\u3044!/Ball care",
   "author": "\u4e2d\u5c3e\u548c\u5b50\u76e3\u4fee",
   "publisher": "\u65e5\u672cG\u30dc\u30fc\u30eb\u5354\u4f1a 20??",
   "isbn": "",
   "holding": "\u4f53\u82b8 781-B65 \u4e00\u822c\u56f3\u66f8",
   "status": "\u914d\u67b6\u6e08",
   "imagesrc": ""
  }
 },
 {
  "index": 94,
  "data": {
   "link": "https://www.tulips.tsukuba.ac.jp/opac/volume/4034528?current=95&total=176&trans_url=%2Fopac%2Fsearch%3Farrivedwithin%3D1%26count%3D100%26defaultpage%3D1%26defaulttarget%3Dlocal%26order%3Darrival_date_d%26searchmode%3Dcomplex%26type%255B%255D%3Dbook",
   "title": "\u30de\u30f3\u30b9\u30d5\u30a3\u30fc\u30eb\u30c9\u30fb\u30d1\u30fc\u30af, \u4e0a",
   "author": "\u30b8\u30a7\u30a4\u30f3\u30fb\u30aa\u30fc\u30b9\u30c6\u30a3\u30f3\u4f5c/\u65b0\u4e95\u6f64\u7f8e, \u5bae\u4e38\u88d5\u4e8c\u8a33",
   "publisher": "\u5ca9\u6ce2\u66f8\u5e97 2021/11",
   "isbn": "9784003222270",
   "holding": "\u4e2d\u592e 081-I95-R222-7 \u4e00\u822c\u56f3\u66f8, \u4f53\u82b8 081-I95-R222-7 \u4e00\u822c\u56f3\u66f8, \u533b\u5b66 081-I95-R222-7 \u4e00\u822c\u56f3\u66f8",
   "status": "\u914d\u67b6\u6e08",
   "imagesrc": "https://books.google.com/books/content?id=RHOyzgEACAAJ&printsec=frontcover&img=1&zoom=5"
  }
 },
 {
  "index": 95,
  "data": {
   "link": "https://www.tulips.tsukuba.ac.jp/opac/volume/4034518?current=96&total=176&trans_url=%2Fopac%2Fsearch%3Farrivedwithin%3D1%26count%3D100%26defaultpage%3D1%26defaulttarget%3Dlocal%26order%3Darrival_date_d%26searchmode%3Dcomplex%26type%255B%255D%3Dbook",
   "title": "\u30e1\u30c7\u30a3\u30a2\u306e\u672a\u6765 : \u6b74\u53f2\u3092\u5b66\u3076\u3053\u3068\u3067\u3001\u65b0\u805e\u3001\u96d1\u8a8c\u3001\u30e9\u30b8\u30aa\u3001\u30c6\u30ec\u30d3\u3001SNS\u306e\u5c06\u6765\u306f\u5c0e\u304d\u51fa\u305b\u308b",
   "author": "\u30b8\u30e3\u30c3\u30af\u30fb\u30a2\u30bf\u30ea\u8457/\u6797\u660c\u5b8f\u8a33",
   "publisher": "\u30d7\u30ec\u30b8\u30c7\u30f3\u30c8\u793e 2021/9",
   "isbn": "9784833424295",
   "holding": "\u56f3\u60c5\u642c\u9001\u4e2d 361.453-A95 \u4e00\u822c\u56f3\u66f8",
   "status": "\u914d\u67b6\u6e08",
   "imagesrc": "https://books.google.com/books/content?id=egSZzgEACAAJ&printsec=frontcover&img=1&zoom=5"
  }
 },
 {
  "index": 96,
  "data": {
   "link": "https://www.tulips.tsukuba.ac.jp/opac/volume/4034473?current=97&total=176&trans_url=%2Fopac%2Fsearch%3Farrivedwithin%3D1%26count%3D100%26defaultpage%3D1%26defaulttarget%3Dlocal%26order%3Darrival_date_d%26searchmode%3Dcomplex%26type%255B%255D%3Dbook",
   "title": "\u6728\u9020\u4f4f\u5b85\u30c7\u30a3\u30c6\u30fc\u30eb\u96c6 : \u7a7a\u9593\u30c7\u30b6\u30a4\u30f3\u306b\u306f\u30bb\u30aa\u30ea\u30fc\u304c\u3042\u308b, \u6700\u65b0\u7248",
   "author": "",
   "publisher": "\u30a8\u30af\u30b9\u30ca\u30ec\u30c3\u30b8 2021/7",
   "isbn": "9784767828787",
   "holding": "\u4f53\u82b8 527.1-Mo21 \u4e00\u822c\u56f3\u66f8",
   "status": "\u914d\u67b6\u6e08",
   "imagesrc": "https://books.google.com/books/content?id=7JWKzgEACAAJ&printsec=frontcover&img=1&zoom=5"
  }
 },
 {
  "index": 97,
  "data": {
   "link": "https://www.tulips.tsukuba.ac.jp/opac/volume/4034482?current=98&total=176&trans_url=%2Fopac%2Fsearch%3Farrivedwithin%3D1%26count%3D100%26defaultpage%3D1%26defaulttarget%3Dlocal%26order%3Darrival_date_d%26searchmode%3Dcomplex%26type%255B%255D%3Dbook",
   "title": "\u30e2\u30c0\u30f3JavaScript\u306e\u57fa\u672c\u304b\u3089\u59cb\u3081\u308bReact\u5b9f\u8df5\u306e\u6559\u79d1\u66f8",
   "author": "\u3058\u3083\u3051\u3047(\u5ca1\u7530\u62d3\u5df3)\u8457",
   "publisher": "SB\u30af\u30ea\u30a8\u30a4\u30c6\u30a3\u30d6 2021/9",
   "isbn": "9784815610722",
   "holding": "\u56f3\u60c5\u642c\u9001\u4e2d 547.483-J16 \u4e00\u822c\u56f3\u66f8",
   "status": "\u914d\u67b6\u6e08",
   "imagesrc": "https://books.google.com/books/content?id=mK9CEAAAQBAJ&printsec=frontcover&img=1&zoom=5&edge=curl"
  }
 },
 {
  "index": 98,
  "data": {
   "link": "https://www.tulips.tsukuba.ac.jp/opac/volume/4034472?current=99&total=176&trans_url=%2Fopac%2Fsearch%3Farrivedwithin%3D1%26count%3D100%26defaultpage%3D1%26defaulttarget%3Dlocal%26order%3Darrival_date_d%26searchmode%3Dcomplex%26type%255B%255D%3Dbook",
   "title": "\u30e8\u30fc\u30ed\u30c3\u30d1\u30fb\u30b5\u30c3\u30ab\u30fc\u3068EU\u6cd5",
   "author": "\u4e95\u4e0a\u5178\u4e4b\u8457",
   "publisher": "\u4fe1\u5c71\u793e 2021/6",
   "isbn": "9784797281071",
   "holding": "\u4f53\u82b8 780-I57-2 \u4e00\u822c\u56f3\u66f8",
   "status": "\u914d\u67b6\u6e08",
   "imagesrc": ""
  }
 },
 {
  "index": 99,
  "data": {
   "link": "https://www.tulips.tsukuba.ac.jp/opac/volume/4034221?current=100&total=176&trans_url=%2Fopac%2Fsearch%3Farrivedwithin%3D1%26count%3D100%26defaultpage%3D1%26defaulttarget%3Dlocal%26order%3Darrival_date_d%26searchmode%3Dcomplex%26type%255B%255D%3Dbook",
   "title": "\u30e9\u30b0\u30d3\u30fc\u306e\u30d5\u30a3\u30b8\u30ab\u30eb\u30c8\u30ec\u30fc\u30cb\u30f3\u30b0",
   "author": "\u592a\u7530\u5343\u5c0b\u8457",
   "publisher": "\u30d9\u30fc\u30b9\u30dc\u30fc\u30eb\u30fb\u30de\u30ac\u30b8\u30f3\u793e 2021/6",
   "isbn": "9784583112473",
   "holding": "\u4f53\u82b8 783.48-O81 \u4e00\u822c\u56f3\u66f8",
   "status": "\u914d\u67b6\u6e08",
   "imagesrc": "https://books.google.com/books/content?id=e6SEzgEACAAJ&printsec=frontcover&img=1&zoom=5"
  }
 }
]
